Workbook

Sheet Portada

Sheet Tablas y Filtros
A10: Torre | B10: Tipo | C10: Modelo | D10: Número de Serie | E10: Descripción | F10: Valor Bruto del Activo | G10: Nuevo o Usado
A11: Medio | B11: 2817 | C11: M49 | D11: 024DE82 | E11: SYSTEM Z10 EC | F11: 5122975.3 | G11: Nuevo
A12: Medio | B12: 3957 | C12: V06 | D12: 78H2884 | E12: VIRTUALIZATION ENGINE TS7740 | F12: 116532.47 | G12: Usado | I12: Criterio | J12: Respuesta
A13: Medio | B13: 3957 | C13: V06 | D13: 78H2919 | E13: VIRTUALIZATION ENGINE TS7740 | F13: 116532.47 | G13: Usado | I13: Valor Bruto de los Activos Nuevos | J13: 5442863
A14: Medio | B14: 3957 | C14: V06 | D14: 78H2829 | E14: VIRTUALIZATION ENGINE TS7740 | F14: 115572.39 | G14: Usado | I14: Valor Bruto de los Activos Usados | J14: 611945
A15: Medio | B15: 3956 | C15: CX7 | D15: 00B3676 | E15: TS7740 CACHE CONTROLLER | F15: 37496.07 | G15: Nuevo | I15: Total de activos con un valor menor a 10,000 USD cada uno | J15: 43
A16: Medio | B16: 3956 | C16: CX7 | D16: 00B3696 | E16: TS7740 CACHE CONTROLLER | F16: 37496.07 | G16: Nuevo | I16: Valor Bruto de todas las máquinas de la Torre Medio | J16: 6010264
A17: Medio | B17: 3956 | C17: CX7 | D17: 00B3938 | E17: TS7740 CACHE CONTROLLER | F17: 37496.07 | G17: Usado | I17: Activo de mayor valor | J17: SYSTEM Z10 EC
A18: Medio | B18: 3956 | C18: CX7 | D18: 00B3939 | E18: TS7740 CACHE CONTROLLER | F18: 37496.07 | G18: Usado
A19: Medio | B19: 3956 | C19: CX7 | D19: 00B3950 | E19: TS7740 CACHE CONTROLLER | F19: 37496.07 | G19: Usado
A20: Medio | B20: 3956 | C20: CX7 | D20: 00B3951 | E20: TS7740 CACHE CONTROLLER | F20: 37496.07 | G20: Usado
A21: Medio | B21: 3584 | C21: L23 | D21: 78A3328 | E21: ULTRIUM ANACONDA LIBRARY | F21: 31497 | G21: Nuevo
A22: Medio | B22: 3584 | C22: D23 | D22: 78D0528 | E22: ULTRIUM ANACONDA LIBRARY | F22: 17911.39 | G22: Nuevo
A23: Medio | B23: 3584 | C23: D23 | D23: 78D0632 | E23: ULTRIUM ANACONDA LIBRARY | F23: 17911.39 | G23: Nuevo
A24: Medio | B24: 3584 | C24: D23 | D24: 78D0974 | E24: ULTRIUM ANACONDA LIBRARY | F24: 17911.39 | G24: Nuevo
A25: Medio | B25: 3584 | C25: D23 | D25: 78D0282 | E25: ULTRIUM ANACONDA LIBRARY | F25: 17868.91 | G25: Nuevo
A26: Medio | B26: 3584 | C26: D23 | D26: 78D0637 | E26: ULTRIUM ANACONDA LIBRARY | F26: 17868.91 | G26: Nuevo
A27: Medio | B27: 1818 | C27: D1A | D27: 00K1Y5X | E27: ASSIGN=EXP5000 EXPANSION UNIT | F27: 15361.15 | G27: Nuevo
A28: Medio | B28: 1740 | C28: 710 | D28: 0000667 | E28: TOTALSTORAGE FASTT EXP700 | F28: 10524 | G28: Nuevo
A29: Medio | B29: 3952 | C29: F05 | D29: 7813534 | E29: ASSIGN TAPE FRAME | F29: 8644.41 | G29: Nuevo
... A52: Medio | B52: 1818 | C52: D1A | D52: 78K1TR7 | E52: ASSIGN=EXP5000 EXPANSION UNIT | F52: 5070.91 | G52: Usado
A53: Servicios | B53: Z814 | D53: TAAS199037329 | E53: PANDUIT NET-ACCESS SWITCH CABINET | F53: 3810.16 | G53: Nuevo
A54: Servicios | B54: Z811 | D54: TAAS199037326 | E54: PANDUIT NET-ACCESS SWITCH CABINET | F54: 3810.15 | G54: Usado
A55: Servicios | B55: Z812 | D55: TAAS199037327 | E55: PANDUIT NET-ACCESS SWITCH CABINET | F55: 3810.15 | G55: Usado
A56: Servicios | B56: Z813 | D56: TAAS199037328 | E56: PANDUIT NET-ACCESS SWITCH CABINET | F56: 3810.15 | G56: Nuevo
A57: Servicios | B57: Z810 | D57: TAAS199037325 | E57: PANDUIT NET-ACCESS SWITCH CABINET | F57: 3809.97 | G57: Usado
A58: Servicios | B58: Z809 | D58: TAAS199037324 | E58: PANDUIT NET-ACCESS SWITCH CABINET | F58: 3809.96 | G58: Usado
A59: Medio | B59: 2145 | C59: CF8 | D59: 00LTG0A | E59: SAN VOLUME CONTROLLER XSERIES | F59: 3774.54 | G59: Usado
A60: Medio | B60: 2145 | C60: CF8 | D60: 00LTCFA | E60: SAN VOLUME CONTROLLER XSERIES | F60: 3773.63 | G60: Usado
A61: Medio | B61: 2145 | C61: CF8 | D61: 75LRRMA | E61: SAN VOLUME CONTROLLER XSERIES | F61: 3773.63 | G61: Usado
A62: Medio | B62: 2805 | C62: MC5 | D62: 0012242 | E62: SYSTEM STORAGE PRODUCT. CENTER | F62: 3367 | G62: Nuevo
A63: Medio | B63: 2805 | C63: MC5 | D63: 7512419 | E63: SYSTEM STORAGE PRODUCT. CENTER | F63: 3367 | G63: Nuevo
A64: Servicios | B64: 4252 | C64: AC1 | D64: KQ60W8R | E64: 4252 AC1 - SERVER | F64: 2798.4 | G64: Usado
A65: Servicios | B65: 4252 | C65: AC1 | D65: KQ60W8T | E65: 4252 AC1 - SERVER | F65: 2798.4 | G65: Usado
A66: Servicios | B66: 4252 | C66: AC1 | D66: KQ60W8V | E66: 4252 AC1 - SERVER | F66: 2798.4 | G66: Usado
A67: Servicios | B67: 4252 | C67: AC1 | D67: KQ60W8W | E67: 4252 AC1 - SERVER | F67: 2798.4 | G67: Usado
A68: Servicios | B68: 4252 | C68: AC1 | D68: KQ60W8X | E68: 4252 AC1 - SERVER | F68: 2798.4 | G68: Usado
A69: Medio | B69: 2145 | C69: CF8 | D69: 00LRRMA | E69: SAN VOLUME CONTROLLER XSERIES | F69: 0 | G69: Usado
A70: Medio | B70: 2805 | C70: MC5 | D70: 0012419 | E70: SYSTEM STORAGE PRODUCT. CENTER | F70: 0 | G70: Nuevo
A71: Servicios | B71: 7947 | C71: AC1 | D71: KQYDBZH | E71: IBM SYSTEM X3650 | F71: 0 | G71: Usado

Sheet Eco Mercado
A17: 18 de Enero | N17: 25 de Enero | AA17: 01 de Febrero | AN17: 08 de Febrero | BB17: 15 de Febrero | BP17: 22 de Febrero | CD17: 01 de Marzo
A18: Empresa | B18: Contacto | C18: Celular | D18: Teléfono | E18: Correo Electrónico | F18: Giro | G18: Vendedor | H18: Forma de Pago | I18: Precio | J18: Mesa | K18: Espacio | L18: Nuevo | N18: Empresa | O18: Contacto | P18: Celular | Q18: Teléfono | R18: Correo Electrónico | S18: Giro | T18: Vendedor | U18: Forma de Pago | V18: Precio | W18: Mesa | X18: Espacio | Y18: Nuevo | AA18: Empresa | AB18: Contacto | AC18: Celular | AD18: Teléfono | AE18: Correo Electrónico | AF18: Giro | AG18: Vendedor | AH18: Forma de Pago | AI18: Precio | AJ18: Mesa | AK18: Espacio | AL18: Nuevo | AN18: Empresa | AO18: Contacto | AP18: Celular | AQ18: Teléfono | AR18: Correo Electrónico | AS18: Giro | AT18: Vendedor | AU18: Forma de Pago | AV18: Precio | AW18: Mesa | AX18: Espacio | AY18: Nuevo | AZ18: Perforación | BB18: Empresa | BC18: Contacto | BD18: Celular | BE18: Teléfono | BF18: Correo Electrónico | BG18: Giro | BH18: Vendedor | BI18: Forma de Pago | BJ18: Precio | BK18: Mesa | BL18: Espacio | BM18: Nuevo | BN18: Perforación | BP18: Empresa | BQ18: Contacto | BR18: Celular | BS18: Teléfono | BT18: Correo Electrónico | BU18: Giro | BV18: Vendedor | BW18: Forma de Pago | BX18: Precio | BY18: Mesa | BZ18: Espacio | CA18: Nuevo | CB18: Perforación | CD18: Empresa | CE18: Contacto | CF18: Celular | CG18: Teléfono | CH18: Correo Electrónico | CI18: Giro | CJ18: Vendedor | CK18: Forma de Pago | CL18: Precio | CM18: Mesa | CN18: Espacio | CO18: Nuevo | CP18: Perforación
A19: A Long Asian Gourmet | B19: Aaron Disler | C19: 3314819409 | E19: a_long_asian_gourmet@yahoo.com | F19: Empanadas chinas, dumplings | H19: Banco | I19: 232 | J19: Media | K19: 18a | N19: 4to de Baño | O19: Gabriela Jiménez | P19: 3311488590 | Q19: 38135725 | R19: gabiwork@hotmail.com | S19: jabones naturales, cepillos | U19: Efectivo | V19: 375 | W19: Completa | X19: 5 | AA19: 4to de Baño | AB19: Gabriela Jiménez | AC19: 3311488590 | AD19: 38135725 | AE19: gabiwork@hotmail.com | AF19: jabones naturales, cepillos | AH19: Efectivo | AI19: 375 | AJ19: Completa | AK19: 5 | AN19: A Long Asian Gourmet | AO19: Aaron Disler | AP19: 3314819409 | AR19: a_long_asian_gourmet@yahoo.com | AS19: Empanadas chinas, dumplings | AU19: Transferencia | AV19: 232 | AW19: Media | AX19: 30a | AZ19: 1 | BB19: 4to de Baño | BC19: Gabriela Jiménez | BD19: 3311488590 | BE19: 38135725 | BF19: gabiwork@hotmail.com | BG19: jabones naturales, cepillos | BI19: Efectivo | BJ19: 375 | BK19: Completa | BL19: 5 | BN19: 1 | BP19: 4to de Baño | BQ19: Gabriela Jiménez | BR19: 3311488590 | BS19: 38135725 | BT19: gabiwork@hotmail.com | BU19: jabones naturales, cepillos | BW19: Efectivo | BX19: 375 | BY19: Completa | BZ19: 16 | CB19: 2 | CD19: A Long Asian Gourmet | CE19: Aaron Disler | CF19: 3314819409 | CH19: a_long_asian_gourmet@yahoo.com | CI19: Empanadas chinas, dumplings | CK19: Transferencia | CL19: 232 | CM19: Media | CN19: 5b | CP19: 4
A20: AMO Cacao | B20: Fernel Bobadilla | C20: 3315337212 | E20: fernelbp@hotmail.com | F20: Chocolate. | H20: Efectivo | I20: 187.5 | J20: Media | K20: 17b | N20: AMO Cacao | O20: Fernel Bobadilla | P20: 3315337212 | R20: fernelbp@hotmail.com | S20: Chocolate. | U20: Efectivo | V20: 187.5 | W20: Media | X20: 17b | AA20: A Long Asian Gourmet | AB20: Aaron Disler | AC20: 3314819409 | AE20: a_long_asian_gourmet@yahoo.com | AF20: Empanadas chinas, dumplings | AH20: Efectivo | AI20: 200 | AJ20: Media | AK20: 23 | AN20: AMO Cacao | AO20: Fernel Bobadilla | AP20: 3315337212 | AR20: fernelbp@hotmail.com | AS20: Chocolate. | AU20: Efectivo | AV20: 187.5 | AW20: Media | AX20: 18b | AZ20: 1 | BB20: A Long Asian Gourmet | BC20: Aaron Disler | BD20: 3314819409 | BF20: a_long_asian_gourmet@yahoo.com | BG20: Empanadas chinas, dumplings | BI20: Banco | BJ20: 232 | BK20: Media | BL20: 31a | BN20: 2 | BP20: A Long Asian Gourmet | BQ20: Aaron Disler | BR20: 3314819409 | BT20: a_long_asian_gourmet@yahoo.com | BU20: Empanadas chinas, dumplings | BW20: Banco | BX20: 232 | BY20: Media | BZ20: 32b | CB20: 3 | CD20: Angie Inzúa | CE20: Angie Inzúa | CF20: 3314174876 | CH20: u2angie@hotmail.com | CI20: collares hechos a mano | CK20: Efectivo | CL20: 187.5 | CM20: Media | CN20: 13b | CP20: 4
A21: Ángeles Queso | B21: Ángeles Queso | C21: 3335591738 | E21: mangelesmunoz@me.com | F21: Quesos, aderezos. | H21: Efectivo | I21: 200 | J21: Media | K21: 3a | N21: Ángeles Queso | O21: Ángeles Queso | P21: 3335591738 | R21: mangelesmunoz@me.com | S21: Quesos, aderezos. | U21: Efectivo | V21: 200 | W21: Media | X21: 3a | AA21: AMO Cacao | AB21: Fernel Bobadilla | AC21: 3315337212 | AE21: fernelbp@hotmail.com | AF21: Chocolate. | AH21: Efectivo | AI21: 187.5 | AJ21: Media | AK21: 17b | AN21: Ángeles Queso | AO21: Ángeles Queso | AP21: 3335591738 | AR21: mangelesmunoz@me.com | AS21: Quesos, aderezos. | AU21: Efectivo | AV21: 100 | AW21: Media | AX21: 11b | AZ21: 1 | BB21: Angie Inzúa | BC21: Angie Inzúa | BD21: 3314174876 | BF21: u2angie@hotmail.com | BG21: collares hechos a mano | BI21: Efectivo | BJ21: 187.5 | BK21: Media | BL21: 13a | BN21: 2 | BP21: AMO Cacao | BQ21: Fernel Bobadilla | BR21: 3315337212 | BT21: fernelbp@hotmail.com | BU21: Chocolate. | BW21: Efectivo | BX21: 190 | BY21: Media | BZ21: 31b | CB21: 2 | CD21: Bambuk | CE21: Santiago Álvarez | CF21: 3338210776 | CH21: alvarezv.santiago@gmail.com | CI21: Fundas de madera para celular | CK21: Efectivo | CL21: 187.5 | CM21: Media | CN21: 9b | CP21: 4
A22: Angie Inzúa | B22: Angie Inzúa | C22: 3314174876 | E22: u2angie@hotmail.com | F22: collares hechos a mano | H22: Efectivo | I22: 187.5 | J22: Media | K22: 13b | N22: Angie Inzúa | O22: Angie Inzúa | P22: 3314174876 | R22: u2angie@hotmail.com | S22: collares hechos a mano | U22: Efectivo | V22: 187.5 | W22: Media | X22: 14a | AA22: Ángeles Queso | AB22: Ángeles Queso | AC22: 3335591738 | AE22: mangelesmunoz@me.com | AF22: Quesos, aderezos. | AH22: Efectivo | AI22: 100 | AJ22: Media | AK22: 3a | AN22: Angie Inzúa | AO22: Angie Inzúa | AP22: 3314174876 | AR22: u2angie@hotmail.com | AS22: collares hechos a mano | AU22: Efectivo | AV22: 187.5 | AW22: Media | AX22: 13a | AZ22: 1 | BB22: Armonía Magnética | BC22: Pilar Ramírez | BD22: 3314177243 | BF22: armoniamagnetica@gmail.com | BI22: Efectivo | BJ22: 200 | BK22: Media | BL22: 20a | BN22: 2 | BP22: Angie Inzúa | BQ22: Angie Inzúa | BR22: 3314174876 | BT22: u2angie@hotmail.com | BU22: collares hechos a mano | BW22: Efectivo | BX22: 187.5 | BY22: Media | BZ22: 13a | CB22: 3 | CD22: Celestial | CE22: Héctor Fajardo | CF22: 3311424137 | CG22: 36159547 | CH22: hectorfajardo1@icloud.com | CI22: especias, pesto, aceite de oliva, sal de mar, tomate deshidratado | CK22: Efectivo | CL22: 200 | CM22: Media | CN22: 3b | CP22: 4
A23: Armonía Magnética | B23: Pilar Ramírez | C23: 3314117724 | E23: armoniamagnetica@gmail.com | H23: Efectivo | I23: 200 | J23: Media | K23: 10a | N23: Avogratto | O23: Lorena Ortiz | P23: 3314872679 | R23: lpatri1304@hotmail.com | S23: Aceite de aguacate. | U23: Anticipado | V23: 0 | W23: Media | X23: 17a | AA23: Angie Inzúa | AB23: Angie Inzúa | AC23: 3314174876 | AE23: u2angie@hotmail.com | AF23: collares hechos a mano | AH23: Efectivo | AI23: 187.5 | AJ23: Media | AK23: 14a | AN23: Armonía Magnética | AO23: Pilar Ramírez | AP23: 3314177243 | AR23: armoniamagnetica@gmail.com | AU23: Efectivo | AV23: 200 | AW23: Media | AX23: 14b | AZ23: 1 | BB23: Aura Rodriguez | BC23: Aura Rodriguez | BD23: 3317711276 | BF23: aura.xacnicte@gmail.com | BG23: Pinturas | BI23: Efectivo | BJ23: 200 | BK23: Media | BL23: 21b | BN23: 2 | BP23: Armonía Magnética | BQ23: Pilar Ramírez | BR23: 3314177243 | BT23: armoniamagnetica@gmail.com | BW23: Efectivo | BX23: 200 | BY23: Media | BZ23: 28b | CB23: 3 | CD23: Che Sen | CE23: Martha Rojo de la Vega | CF23: 3339559274 | CH23: contacto.chesen@gmail.com | CI23: granola, nueces | CK23: Efectivo | CL23: 187.5 | CM23: Media | CN23: 5a | CP23: 4
A24: Avogratto | B24: Lorena Ortiz | C24: 3314872679 | E24: lpatri1304@hotmail.com | F24: Aceite de aguacate. | H24: Anticipado | I24: 0 | J24: Media | K24: 17a | N24: Azafrán Boxes | O24: Leonardo Parra | P24: 3331294429 | R24: azafranboxes@gmail.com | S24: cajas fuertes en forma de libros | T24: Sofía | U24: pendiente | V24: 200 | W24: Media | X24: 21b | AA24: Aura Rodriguez | AB24: Aura Rodriguez | AC24: 3317711276 | AE24: aura.xacnicte@gmail.com | AF24: Pinturas | AH24: Efectivo | AI24: 200 | AJ24: Media | AK24: 21b | AN24: Aura Rodriguez | AO24: Aura Rodriguez | AP24: 3317711276 | AR24: aura.xacnicte@gmail.com | AS24: Pinturas | AU24: Efectivo | AV24: 200 | AW24: Media | AX24: 20b | AZ24: 1 | BB24: Avogratto | BC24: Lorena Ortiz | BD24: 3314872679 | BF24: lpatri1304@hotmail.com | BG24: Aceite de aguacate. | BI24: Anticipado | BJ24: 0 | BK24: Media | BL24: 17b | BN24: 2 | BP24: Aura Rodriguez | BQ24: Aura Rodriguez | BR24: 3317711276 | BT24: aura.xacnicte@gmail.com | BU24: Pinturas | BW24: Efectivo | BX24: 200 | BY24: Media | BZ24: 21b | CB24: 3 | CD24: Cosas para Gato | CE24: Alejandra Montes de Oca | CF24: 3312148735 | CG24: 18160501 | CH24: cosasparagatos@gmail.com | CI24: Artículos para mascotas | CK24: Efectivo | CL24: 200 | CM24: Ninguna | CP24: 0
A25: Bambuk | B25: Santiago Álvarez | C25: 3338210776 | E25: alvarezv.santiago@gmail.com | F25: fundas de madera para celular | H25: Efectivo | I25: 187.5 | J25: Media | K25: 9b | N25: Bambuk | O25: Santiago Álvarez | P25: 3338210776 | R25: alvarezv.santiago@gmail.com | S25: fundas de madera para celular | U25: Efectivo | V25: 187.5 | W25: Media | X25: 9b | AA25: Avogratto | AB25: Lorena Ortiz | AC25: 3314872679 | AE25: lpatri1304@hotmail.com | AF25: Aceite de aguacate. | AH25: Efectivo | AI25: 0 | AJ25: Media | AK25: 18b | AN25: Avogratto | AO25: Lorena Ortiz | AP25: 3314872679 | AR25: lpatri1304@hotmail.com | AS25: Aceite de aguacate. | AU25: Anticipado | AV25: 0 | AW25: Media | AX25: 17b | AZ25: 1 | BB25: Bambuk | BC25: Santiago Álvarez | BD25: 3338210776 | BF25: alvarezv.santiago@gmail.com | BG25: Fundas de madera para celular | BI25: Efectivo | BJ25: 187.5 | BK25: Media | BL25: 9b | BN25: 2 | BP25: Azafrán Boxes | BQ25: Leonardo Parra | BR25: 3331294429 | BT25: azafranboxes@gmail.com | BU25: cajas fuertes en forma de libros | BW25: Pendiente | BX25: 250 | BY25: Media | BZ25: 35a | CB25: 1 | CD25: D'Talles y Bisutería | CE25: Adrián Martínez | CF25: 3310932686 | CH25: dtalle@hotmail.com | CI25: relojes, pulseras, llaveros, accesorios | CJ25: Sofía | CK25: Efectivo | CL25: 187.5 | CM25: Media | CN25: 6b | CP25: 4
A26: Bernardo Brocher | B26: Bernardo Brocher | C26: 3331979100 | E26: barneybrocher@hotmail.com | F26: Empanadas y embutidos. | H26: Efectivo | I26: 200 | J26: Media | K26: 11a | N26: Bio Zen | O26: Areli Arámbula | P26: 3310508101 | R26: karenalonsogarza@gmail.com | S26: Desodorante de piedra. | T26: Sofía | X26: 2 | AA26: Bambuk | AB26: Santiago Álvarez | AC26: 3338210776 | AE26: alvarezv.santiago@gmail.com | AF26: fundas de madera para celular | AH26: Efectivo | AI26: 187.5 | AJ26: Media | AK26: 9b | AN26: Bambú | AO26: Ofelia Fernández | AP26: 3315716643 | AQ26: 33303837 | AR26: bambualmohadasterapeuticas@gmail.com | AS26: Almohadas terapéuticas. | AU26: Efectivo | AV26: 375 | AW26: Completa | AX26: 5 | AZ26: 1 | BB26: Biorganicos FG | BC26: Flor López Bon | BD26: 333 6622520 | BE26: 36272470 | BF26: biorganicosfg@gmail.com | BG26: verduras orgánicas | BI26: Efectivo | BJ26: 60 | BK26: Completa | BL26: 11 | BN26: 1 | BP26: Bambú | BQ26: Ofelia Fernández | BR26: 3315716643 | BS26: 33303837 | BT26: bambualmohadasterapeuticas@gmail.com | BU26: Almohadas terapéuticas. | BW26: Efectivo | BX26: 375 | BY26: Completa | BZ26: 17 | CB26: 2 | CD26: Den Maya Invernaderos | CE26: Yesica Delgado Díaz | CF26: 3311856312 | CH26: yeska_27@hotmail.com | CI26: Plantas, hierbas aromáticas, flores, árboles en maceta. | CK26: Efectivo | CL26: 375 | CM26: Completa | CN26: 1 | CP26: 4
A27: Bitácora | B27: Mario de Santos | C27: 3336761496 | E27: mdesantosj@gmail.com | F27: Libretas | G27: Sofía | H27: Efectivo | I27: 187.5 | J27: Media | K27: 21b | N27: Bitácora | O27: Mario de Santos | P27: 3336761496 | R27: mdesantosj@gmail.com | S27: Libretas | T27: Sofía | U27: Efectivo | V27: 187.5 | W27: Media | X27: 6b | AA27: Bernardo Brocher | AB27: Bernardo Brocher | AC27: 3331979100 | AE27: barneybrocher@hotmail.com | AF27: Empanadas y embutidos. | AH27: Efectivo | AI27: 200 | AJ27: Media | AK27: 8a | AN27: Bambuk | AO27: Santiago Álvarez | AP27: 3338210776 | AR27: alvarezv.santiago@gmail.com | AS27: fundas de madera para celular | AU27: Efectivo | AV27: 187.5 | AW27: Media | AX27: 9b | AZ27: 1 | BB27: Celestial | BC27: Héctor Fajardo | BD27: 3311424137 | BE27: 36159547 | BF27: hectorfajardo1@icloud.com | BG27: especias, pesto, aceite de oliva, sal de mar, tomate deshidratado | BI27: Efectivo | BJ27: 200 | BK27: Media | BL27: 3b | BN27: 2 | BP27: Bambuk | BQ27: Santiago Álvarez | BR27: 3338210776 | BT27: alvarezv.santiago@gmail.com | BU27: Fundas de madera para celular | BW27: Efectivo | BX27: 187.5 | BY27: Media | BZ27: 19a | CB27: 3 | CD27: Eclectic | CE27: Osvaldo López | CF27: 3312326066 | CH27: osvaldo_flb@hotmail.com | CI27: Playeras sublimadas | CJ27: Gonzalo | CK27: Falta | CL27: 60 | CM27: Media | CN27: 16a | CP27: 2
A28: Celestial | B28: Héctor Fajardo | C28: 3311424137 | D28: 36159547 | E28: hectorfajardo1@icloud.com | F28: especias, pesto, aceite de oliva, sal de mar, tomate deshidratado | H28: Efectivo | I28: 200 | J28: Media | K28: 16a | N28: Celestial | O28: Héctor Fajardo | P28: 3311424137 | Q28: 36159547 | R28: hectorfajardo1@icloud.com | S28: especias, pesto, aceite de oliva, sal de mar, tomate deshidratado | U28: Efectivo | V28: 200 | W28: Media | X28: 3b | AA28: Bitácora | AB28: Mario de Santos | AC28: 3336761496 | AE28: mdesantosj@gmail.com | AF28: Libretas | AG28: Sofía | AH28: Efectivo | AI28: 187.5 | AJ28: Media | AK28: 6b | AN28: Bernardo Brocher | AO28: Bernardo Brocher | AP28: 3331979100 | AR28: barneybrocher@hotmail.com | AS28: Empanadas y embutidos. | AU28: Efectivo | AV28: 200 | AW28: Media | AX28: 11a | AZ28: 1 | BB28: Che Sen | BC28: Martha Rojo de la Vega | BD28: 3339559274 | BF28: contacto.chesen@gmail.com | BG28: granola, nueces | BI28: Efectivo | BJ28: 187.5 | BK28: Media | BL28: 16b | BN28: 2 | BP28: Biopiscinas | BQ28: Sandra Saldívar | BR28: 3310906593 | BT28: sandra.saldivar@gmail.com | BU28: Sustituto de cloro para albercas y para desinfectar | BV28: Sofía | BW28: Intercambio | BX28: 0 | BY28: Media | BZ28: 34b | CB28: 1 | CD28: Eclock | CE28: Edgar Torres | CF28: 3317246984 | CH28: eclock.relojes@hotmail.com | CI28: Relojes de madera | CK28: Efectivo | CL28: 200 | CM28: Media | CN28: 9a | CP28: 2
A29: Che Sen | B29: Martha Rojo de la Vega | C29: 3339559274 | E29: contacto.chesen@gmail.com | F29: granola, nueces | H29: Banco | I29: 232 | J29: Media | K29: 9a | N29: Che Sen | O29: Martha Rojo de la Vega | P29: 3339559274 | R29: contacto.chesen@gmail.com | S29: granola, nueces | U29: Efectivo | V29: 200 | W29: Media | X29: 9a | AA29: Celestial | AB29: Héctor Fajardo | AC29: 3311424137 | AD29: 36159547 | AE29: hectorfajardo1@icloud.com | AF29: especias, pesto, aceite de oliva, sal de mar, tomate deshidratado | AH29: Efectivo | AI29: 200 | AJ29: Media | AK29: 3b | AN29: Bitácora | AO29: Mario de Santos | AP29: 3336761496 | AR29: mdesantosj@gmail.com | AS29: Libretas | AT29: Sofía | AU29: Efectivo | AV29: 187.5 | AW29: Media | AX29: 32a | AZ29: 1 | BB29: Da Du Didactics | BC29: Ana Elena Peinado Olvera | BD29: 3338304373 | BE29: 10990107 | BF29: anel.dragonas@gmail.com | BG29: juguetes creativos y didácticos de madera | BI29: Intercambio | BJ29: 0 | BK29: Media | BL29: 13b | BN29: 2 | BP29: Celestial | BQ29: Héctor Fajardo | BR29: 3311424137 | BS29: 36159547 | BT29: hectorfajardo1@icloud.com | BU29: especias, pesto, aceite de oliva, sal de mar, tomate deshidratado | BW29: Efectivo | BX29: 200 | BY29: Media | BZ29: 9b | CB29: 3 | CD29: Enjoy Time | CE29: Francisco Valencia | CF29: 3339582509 | CI29: Tisanas frutales y moringa. | CK29: Efectivo | CL29: 400 | CM29: Completa | CN29: 10 | CP29: 4
A30: Da Du Didactics | B30: Ana Elena Peinado Olvera | C30: 3338304373 | D30: 10990107 | E30: anel.dragonas@gmail.com | F30: juguetes creativos y didácticos de madera | H30: Banco | I30: 870 | J30: Media | K30: 13a | N30: Cocina Icaza | O30: Mónica Icaza | P30: 3333778377 | R30: cocinaicaza@gmail.com | S30: Salsas y aderezos. | T30: Sofía | U30: Efectivo | V30: 200 | W30: Media | X30: 10a | AA30: Coco Energy | AB30: Celia Delgadillo | AC30: 3311346872 | AD30: 36988513 | AE30: cedel4@hotmail.com | AF30: aceite de coco | AH30: Efectivo | AI30: 0 | AJ30: Media | AK30: 20 | AN30: Celestial | AO30: Héctor Fajardo | AP30: 3311424137 | AQ30: 36159547 | AR30: hectorfajardo1@icloud.com | AS30: especias, pesto, aceite de oliva, sal de mar, tomate deshidratado | AU30: Efectivo | AV30: 200 | AW30: Media | AX30: 3b | AZ30: 1 | BB30: Den Maya Invernaderos | BC30: Yesica Delgado Díaz | BD30: 3311856312 | BF30: yeska_27@hotmail.com | BG30: Plantas, hierbas aromáticas, flores, árboles en maceta. | BI30: Efectivo | BJ30: 375 | BK30: Completa | BL30: 1 | BN30: 2 | BP30: Che Sen | BQ30: Martha Rojo de la Vega | BR30: 3339559274 | BT30: contacto.chesen@gmail.com | BU30: granola, nueces | BW30: Falta | BX30: 187.5 | BY30: Media | BZ30: 31a | CB30: 3 | CD30: EVOO | CE30: Margarita Rodriguez | CF30: 3313600806 | CH30: dramarrod@hotmail.com | CK30: Efectivo | CL30: 50 | CM30: Completa | CN30: 11 | CP30: 4
A31: Donaji | B31: Nicole Velez Rodriguez | C31: 3319765566 | E31: donajiproductodeoaxaca@gmail.com | F31: mole, café, chocolate, salsas | H31: Efectivo | I31: 250 | J31: Media | K31: Falta | N31: Da Du Didactics | O31: Ana Elena Peinado Olvera | P31: 3338304373 | Q31: 10990107 | R31: anel.dragonas@gmail.com | S31: juguetes creativos y didácticos de madera | U31: Banco | V31: 870 | W31: Media | X31: 13a | AA31: Da Du Didactics | AB31: Ana Elena Peinado Olvera | AC31: 3338304373 | AD31: 10990107 | AE31: anel.dragonas@gmail.com | AF31: juguetes creativos y didácticos de madera | AH31: Banco | AI31: 187.5 | AJ31: Media | AK31: 13b | AN31: Che Sen | AO31: Martha Rojo de la Vega | AP31: 3339559274 | AR31: contacto.chesen@gmail.com | AS31: granola, nueces | AU31: Efectivo | AV31: 187.5 | AW31: Media | AX31: 16b | AZ31: 1 | BB31: D'Talles y Bisutería | BC31: Adrián Martínez | BD31: 3310932686 | BF31: dtalle@hotmail.com | BG31: relojes, pulseras, llaveros, accesorios | BH31: Sofía | BI31: Efectivo | BJ31: 187.5 | BK31: Media | BL31: 6b | BN31: 2 | BP31: Claudia Amador Bisutería | BQ31: Claudia Amador | BR31: 3311092077 | BS31: 16773310 | BT31: clau_75_mx@hotmail.com | BU31: bisutería artesanal | BW31: Efectivo | BX31: 200 | BY31: Media | BZ31: 23b | CB31: 1 | CD31: Gusto Gourmet | CE31: Karen Alonso | CF31: 3314412645 | CI31: Salsas, verdura botanera, chimichurri, pesto. | CK31: Efectivo | CL31: 200 | CM31: Media | CN31: 3a | CP31: 4
A32: Eclock | B32: Edgar Torres | C32: 3317246984 | E32: eclock.relojes@hotmail.com | F32: Relojes de madera | H32: Efectivo | I32: 200 | J32: Media | K32: 21a | N32: Den Maya Invernaderos | O32: Yesica Delgado Díaz | P32: 3311856312 | R32: yeska_27@hotmail.com | S32: Plantas, hierbas aromáticas, flores, árboles en maceta. | U32: Efectivo | V32: 1500 | W32: Completa | X32: 1 | AA32: Den Maya Invernaderos | AB32: Yesica Delgado Díaz | AC32: 3311856312 | AE32: yeska_27@hotmail.com | AF32: Plantas, hierbas aromáticas, flores, árboles en maceta. | AH32: Efectivo | AI32: 375 | AJ32: Completa | AK32: 1 | AN32: Da Du Didactics | AO32: Ana Elena Peinado Olvera | AP32: 3338304373 | AQ32: 10990107 | AR32: anel.dragonas@gmail.com | AS32: juguetes creativos y didácticos de madera | AU32: Banco | AV32: 187.5 | AW32: Media | AX32: 13b | AZ32: 1 | BB32: Eclock | BC32: Edgar Torres | BD32: 3317246984 | BF32: eclock.relojes@hotmail.com | BG32: Relojes de madera | BI32: Efectivo | BJ32: 200 | BK32: Media | BL32: 9a | BN32: 1 | BP32: Cocina Icaza | BQ32: Mónica Icaza | BR32: 3333778377 | BT32: cocinaicaza@gmail.com | BU32: Salsas y aderezos. | BW32: Efectivo | BX32: 125 | BY32: Media | BZ32: 19b | CB32: 1 | CD32: Itacate | CE32: Swannie Díaz de León | CF32: 3310967806 | CH32: yolohtli@gmail.com | CI32: Granola, hummus, tabule, pan. | CK32: Efectivo | CL32: 125 | CM32: Media | CN32: 14b | CP32: 2
A33: EVOO | B33: Margarita Rodriguez | C33: 3313600806 | E33: dramarrod@hotmail.com | H33: Intercambio | I33: 0 | J33: Completa | K33: 1 | N33: Detalles y Bisutería | O33: Adrián Martínez | P33: 3310932686 | R33: dtalle@hotmail.com | U33: Efectivo | V33: 250 | W33: Media | X33: 23a | AA33: Detalles y Bisutería | AB33: Adrián Martínez | AC33: 3310932686 | AE33: dtalle@hotmail.com | AF33: relojes, pulseras, llaveros, accesorios | AG33: Sofía | AH33: Efectivo | AI33: 187.5 | AJ33: Media | AK33: 6b | AN33: Den Maya Invernaderos | AO33: Yesica Delgado Díaz | AP33: 3311856312 | AR33: yeska_27@hotmail.com | AS33: Plantas, hierbas aromáticas, flores, árboles en maceta. | AU33: Efectivo | AV33: 375 | AW33: Completa | AX33: 1 | AZ33: 1 | BB33: Enjoy Time | BC33: Francisco Valencia | BD33: 3339582509 | BG33: Tisanas frutales y moringa. | BI33: Efectivo | BJ33: 400 | BK33: Completa | BL33: 10 | BN33: 2 | BP33: D'Talles y Bisutería | BQ33: Adrián Martínez | BR33: 3310932686 | BT33: dtalle@hotmail.com | BU33: relojes, pulseras, llaveros, accesorios | BV33: Sofía | BW33: Efectivo | BX33: 187.5 | BY33: Media | BZ33: 14b | CB33: 3 | CD33: Jamaitingas | CE33: Arlene Sánchez | CF33: 3334057358 | CH33: miryana23@hotmail.com | CI33: guisados a base de jamaica | CK33: Efectivo | CL33: 200 | CM33: Media | CN33: 15a | CP33: 4
A34: Frutas Vero | B34: Verónica Tolentino Espinoza | C34: 3314277826 | F34: Frutas orgánicas | H34: Efectivo | I34: 50 | J34: Completa | K34: 12 | N34: EVOO | O34: Margarita Rodriguez | P34: 3313600806 | R34: dramarrod@hotmail.com | T34: Margarita | U34: pendiente | V34: 50 | W34: Completa | X34: 22 | AA34: Eclock | AB34: Edgar Torres | AC34: 3317246984 | AE34: eclock.relojes@hotmail.com | AF34: Relojes de madera | AH34: Efectivo | AI34: 200 | AJ34: Media | AK34: 16b | AN34: D'Talles y Bisutería | AO34: Adrián Martínez | AP34: 3310932686 | AR34: dtalle@hotmail.com | AS34: relojes, pulseras, llaveros, accesorios | AT34: Sofía | AU34: Efectivo | AV34: 187.5 | AW34: Media | AX34: 6b | AZ34: 1 | BB34: EVOO | BC34: Margarita Rodriguez | BD34: 3313600806 | BF34: dramarrod@hotmail.com | BI34: Efectivo | BJ34: 50 | BK34: Completa | BL34: 30 | BN34: 2 | BP34: Da Du Didactics | BQ34: Ana Elena Peinado Olvera | BR34: 3338304373 | BS34: 10990107 | BT34: anel.dragonas@gmail.com | BU34: juguetes creativos y didácticos de madera | BW34: Pendiente | BX34: 187.5 | BY34: Media | BZ34: 13b | CB34: 3 | CD34: La Bee Organic | CE34: Luis Elizondo | CF34: 3331787364 | CH34: labeeorganic@gmail.com | CI34: bálsamo para labios | CK34: Efectivo | CL34: 200 | CM34: Media | CN34: 12a | CP34: 3
A35: Glow | B35: Alejandro Cantú | C35: 3317314958 | D35: 17314958 | E35: glowstore.07@gmail.com | F35: ropa de diseño independiente | H35: Efectivo | I35: 750 | J35: Media | K35: 14a | N35: Frutas Vero | O35: Verónica Tolentino Espinoza | P35: 3314277826 | S35: Frutas orgánicas | U35: Efectivo | V35: 50 | W35: Completa | X35: 12 | AA35: Enjoy Time | AB35: Francisco Valencia | AC35: 3339582509 | AF35: Tisanas frutales y moringa. | AH35: Efectivo | AI35: 500 | AJ35: Completa | AK35: 10 | AN35: Enjoy Time | AO35: Francisco Valencia | AP35: 3339582509 | AS35: Tisanas frutales y moringa. | AU35: Efectivo | AV35: 400 | AW35: Completa | AX35: 10 | AZ35: 1 | BB35: Glow | BC35: Alejandro Cantú | BD35: 3317314958 | BE35: 17314958 | BF35: glowstore.07@gmail.com | BG35: ropa de diseño independiente | BI35: Efectivo | BJ35: 187.5 | BK35: Media | BL35: 13c | BN35: 1 | BP35: Den Maya Invernaderos | BQ35: Yesica Delgado Díaz | BR35: 3311856312 | BT35: yeska_27@hotmail.com | BU35: Plantas, hierbas aromáticas, flores, árboles en maceta. | BW35: Efectivo | BX35: 375 | BY35: Completa | BZ35: 6 | CB35: 3 | CD35: La Ciudad de los Campos | CE35: Ángeles Muñoz | CF35: 3335591738 | CH35: mangelesmunoz@me.com | CI35: Quesos, aderezos. | CK35: Efectivo | CL35: 100 | CM35: Media | CN35: 4a | CP35: 4
A36: Gusto Gourmet | B36: Karen Alonso | C36: 3314412645 | F36: Salsas, verdura botanera, chimichurri, pesto. | H36: Efectivo | I36: 200 | J36: Media | K36: 2 | N36: Gaia EcoStore | O36: Viviana Torres | P36: 3318451485 | R36: vivianatorres@gaiaecostore.com | S36: Tienda de productos organicos. | T36: Sofía | U36: pendiente | V36: 50 | W36: Completa | X36: 24 | AA36: EVOO | AB36: Margarita Rodriguez | AC36: 3313600806 | AE36: dramarrod@hotmail.com | AH36: Efectivo | AI36: 50 | AJ36: Completa | AK36: 30 | AN36: EVOO | AO36: Margarita Rodriguez | AP36: 3313600806 | AR36: dramarrod@hotmail.com | AU36: Efectivo | AV36: 50 | AW36: Completa | AX36: 31 | AZ36: 1 | BB36: Gusto Gourmet | BC36: Karen Alonso | BD36: 3314412645 | BG36: Salsas, verdura botanera, chimichurri, pesto. | BI36: Efectivo | BJ36: 200 | BK36: Media | BL36: 3a | BN36: 2 | BP36: Eclectic | BQ36: Osvaldo López | BR36: 3312326066 | BT36: osvaldo_flb@hotmail.com | BU36: Playeras sublimadas | BV36: Gonzalo | BW36: Efectivo | BX36: 250 | BY36: Media | BZ36: 20a | CA36: N | CB36: 1 | CD36: Le Guttie | CE36: Mariel Gutierrez | CF36: 3311392611 | CH36: leguttie@gmail.com | CI36: manzanas cubiertas, fresas con chocolate | CK36: Efectivo | CL36: 200 | CM36: Media | CP36: 3
A37: Jamaitingas | B37: Arlene Sánchez | C37: 3334057358 | E37: miryana23@hotmail.com | F37: guisados a base de jamaica | H37: Efectivo | I37: 750 | J37: Media | K37: 15a | N37: Glow | O37: Alejandro Cantú | P37: 3317314958 | Q37: 17314958 | R37: glowstore.07@gmail.com | S37: ropa de diseño independiente | U37: Efectivo | V37: 750 | W37: Media | X37: 13b | AA37: Gaia EcoStore | AB37: Viviana Torres | AC37: 3318451485 | AE37: vivianatorres@gaiaecostore.com | AF37: Tienda de productos organicos. | AH37: Intercambio | AI37: 50 | AJ37: Completa | AK37: 4 | AN37: Gaia EcoStore | AO37: Viviana Torres | AP37: 3318451485 | AR37: vivianatorres@gaiaecostore.com | AS37: Tienda de productos organicos. | AU37: Efectivo | AV37: 50 | AW37: Completa | AX37: 4 | AZ37: 1 | BB37: Itacate | BC37: Swannie Díaz de León | BD37: 3310967806 | BF37: yolohtli@gmail.com | BG37: Granola, hummus, tabule, pan. | BI37: Efectivo | BJ37: 125 | BK37: Media | BL37: 14b | BN37: 1 | BP37: Eclock | BQ37: Edgar Torres | BR37: 3317246984 | BT37: eclock.relojes@hotmail.com | BU37: Relojes de madera | BW37: Efectivo | BX37: 200 | BY37: Media | BZ37: 24b | CB37: 1 | CD37: Liliana Jaime | CE37: Liliana Gutierrez | CF37: 3314103650 | CH37: lilianajaime78@gmail.com | CI37: ropa de diseño independiente | CJ37: Sofía | CK37: Efectivo | CL37: 200 | CM37: Ninguna | CN37: 10c | CP37: 4
A38: Klok | B38: María Luisa Álvarez Caloca | C38: 3336777441 | D38: 38231337 | E38: maria@xtal.com.mx | F38: Ilustración a base de primacolor. | G38: Gonzalo | H38: Efectivo | I38: 250 | J38: Media | K38: 19a | L38: N | N38: Jamaitingas | O38: Arlene Sánchez | P38: 3334057358 | R38: miryana23@hotmail.com | S38: guisados a base de jamaica | U38: Efectivo | V38: 750 | W38: Media | X38: 15a | AA38: Glow | AB38: Alejandro Cantú | AC38: 3317314958 | AD38: 17314958 | AE38: glowstore.07@gmail.com | AF38: ropa de diseño independiente | AH38: Efectivo | AI38: 187.5 | AJ38: Media | AK38: 13c | AN38: Gusto Gourmet | AO38: Karen Alonso | AP38: 3314412645 | AS38: Salsas, verdura botanera, chimichurri, pesto. | AU38: Efectivo | AV38: 200 | AW38: Media | AX38: 3a | AZ38: 1 | BB38: Jamaitingas | BC38: Arlene Sánchez | BD38: 3334057358 | BF38: miryana23@hotmail.com | BG38: guisados a base de jamaica | BI38: Falta | BJ38: 60 | BK38: Media | BN38: 2 | BP38: Enjoy Time | BQ38: Francisco Valencia | BR38: 3339582509 | BU38: Tisanas frutales y moringa. | BW38: Efectivo | BX38: 400 | BY38: Completa | BZ38: 10 | CB38: 3 | CD38: Lucy Cactus Company | CE38: Verónica Gil | CF38: 3311185434 | CH38: veronik339.vg@gmail.com | CI38: macetas de barro pintadas | CK38: Efectivo | CL38: 187.5 | CM38: Media | CN38: 6a | CP38: 4
A39: La Bee Organic | B39: Luis Elizondo | C39: 3331787364 | E39: labeeorganic@gmail.com | F39: bálsamo para labios | H39: Efectivo | I39: 750 | J39: Media | K39: 14b | N39: Klok | O39: María Luisa Álvarez Caloca | P39: 3336777441 | Q39: 38231337 | R39: maria@xtal.com.mx | S39: Ilustración a base de primacolor. | T39: Gonzalo | U39: Efectivo | V39: 200 | W39: Media | X39: 19a | AA39: Jamaitingas | AB39: Arlene Sánchez | AC39: 3334057358 | AE39: miryana23@hotmail.com | AF39: guisados a base de jamaica | AH39: Efectivo | AI39: 187.5 | AJ39: Media | AK39: 15a | AN39: Jamaitingas | AO39: Arlene Sánchez | AP39: 3334057358 | AR39: miryana23@hotmail.com | AS39: guisados a base de jamaica | AU39: Falta | AV39: 187.5 | AW39: Media | AZ39: 1 | BB39: Klok | BC39: María Luisa Álvarez Caloca | BD39: 3336777441 | BE39: 38231337 | BF39: maria@xtal.com.mx | BG39: Ilustración a base de primacolor. | BH39: Gonzalo | BI39: Efectivo | BJ39: 200 | BK39: Media | BL39: 19a | BN39: 2 | BP39: EVOO | BQ39: Margarita Rodriguez | BR39: 3313600806 | BT39: dramarrod@hotmail.com | BW39: Efectivo | BX39: 50 | BY39: Completa | BZ39: 30 | CB39: 3 | CD39: Mishu | CE39: Ella Cornejo | CF39: 3314415732 | CG39: 36275564 | CH39: ella.marina.cornejo@gmail.com | CI39: Armonizadores de espacios tejidos. | CJ39: Sofía | CK39: Efectivo | CL39: 187.5 | CM39: Media | CN39: 15b | CP39: 4
A40: Le Guttie | B40: Mariel Gutierrez | C40: 3311392611 | E40: leguttie@gmail.com | F40: manzanas cubiertas, fresas con chocolate | H40: Efectivo | I40: 750 | J40: Media | K40: 5b | N40: La Bee Organic | O40: Luis Elizondo | P40: 3331787364 | R40: labeeorganic@gmail.com | S40: bálsamo para labios | U40: Efectivo | V40: 750 | W40: Media | X40: 14b | AA40: Klok | AB40: María Luisa Álvarez Caloca | AC40: 3336777441 | AD40: 38231337 | AE40: maria@xtal.com.mx | AF40: Ilustración a base de primacolor. | AG40: Gonzalo | AH40: Efectivo | AI40: 200 | AJ40: Media | AK40: 5 | AN40: La Bee Organic | AO40: Luis Elizondo | AP40: 3331787364 | AR40: labeeorganic@gmail.com | AS40: bálsamo para labios | AU40: Efectivo | AV40: 187.5 | AW40: Media | AX40: 14a | AZ40: 1 | BB40: La Ciudad de los Campos | BC40: Ángeles Muñoz | BD40: 3335591738 | BF40: mangelesmunoz@me.com | BG40: Quesos, aderezos. | BI40: Efectivo | BJ40: 100 | BK40: Media | BL40: 4a | BN40: 2 | BP40: Gaia EcoStore | BQ40: Viviana Torres | BR40: 3318451485 | BT40: vivianatorres@gaiaecostore.com | BU40: Tienda de productos organicos. | BW40: Efectivo | BX40: 50 | BY40: Completa | BZ40: 11 | CB40: 2 | CD40: MontPao | CE40: Rodrigo Juárez Salazar | CF40: 3315508402 | CH40: borrego_gdl@hotmail.com | CI40: Blueberrys, mermeladas. | CJ40: Sofía | CK40: Efectivo | CL40: 187.5 | CM40: Media | CN40: 2a | CP40: 4
A41: Lovely Creations | B41: Luz Mantilla | C41: 3339683396 | E41: itza.barba@hp.com | H41: Efectivo | I41: 400 | J41: Completa | K41: 7 | N41: Le Guttie | O41: Mariel Gutierrez | P41: 3311392611 | R41: leguttie@gmail.com | S41: manzanas cubiertas, fresas con chocolate | U41: Efectivo | V41: 750 | W41: Media | X41: 10b | AA41: Korkas | AB41: Aranzazú Castillo | AC41: 3319582152 | AE41: aranza.dicastello@hotmail.com | AF41: sandalias artesanales | AH41: Efectivo | AI41: 200 | AJ41: Media | AK41: 16a | AN41: Le Guttie | AO41: Mariel Gutierrez | AP41: 3311392611 | AR41: leguttie@gmail.com | AS41: manzanas cubiertas, fresas con chocolate | AU41: Efectivo | AV41: 187.5 | AW41: Media | AX41: 9a | AZ41: 1 | BB41: Le Guttie | BC41: Mariel Gutierrez | BD41: 3311392611 | BF41: leguttie@gmail.com | BG41: manzanas cubiertas, fresas con chocolate | BI41: Falta | BJ41: 60 | BK41: Media | BN41: 2 | BP41: Glow | BQ41: Alejandro Cantú | BR41: 3317314958 | BS41: 17314958 | BT41: glowstore.07@gmail.com | BU41: ropa de diseño independiente | BW41: Efectivo | BX41: 200 | BY41: Ninguna | BZ41: 13c | CB41: 2 | CD41: Nacuii | CE41: Denis Ruan | CF41: 3339576724 | CH41: denis@nacuii.com | CI41: Productos de concha nacar y madreperla. | CJ41: Gonzalo | CK41: Efectivo | CL41: 200 | CM41: Media | CN41: 13a | CO41: N | CP41: 1
A42: Lucy Cactus Company | B42: Verónica Gil | C42: 3311185434 | E42: veronik339.vg@gmail.com | F42: macetas de barro pintadas | H42: Efectivo | I42: 200 | J42: Media | K42: 20a | N42: Libertas | O42: Luis Felipe Angulo | P42: 3310640389 | R42: lufac90@hotmail.com | S42: Licor de jamaica. | T42: Margarita | U42: pendiente | V42: 750 | W42: Media | X42: 16b | AA42: Le Guttie | AB42: Mariel Gutierrez | AC42: 3311392611 | AE42: leguttie@gmail.com | AF42: manzanas cubiertas, fresas con chocolate | AH42: Efectivo | AI42: 187.5 | AJ42: Media | AK42: 8b | AN42: Le Ve | AO42: Brenda de la Cruz | AP42: 3312088704 | AR42: bleutulip@hotmail.com | AS42: Quesos y leches veganos de semillas | AT42: Ceci | AU42: Efectivo | AV42: 200 | AW42: Media | AX42: 17a | AZ42: 1 | BB42: Le Ve | BC42: Brenda de la Cruz | BD42: 3312088704 | BF42: bleutulip@hotmail.com | BG42: Quesos y leches veganos de semillas | BH42: Ceci | BI42: Efectivo | BJ42: 200 | BK42: Media | BL42: 17a | BN42: 2 | BP42: Gusto Gourmet | BQ42: Karen Alonso | BR42: 3314412645 | BU42: Salsas, verdura botanera, chimichurri, pesto. | BW42: Efectivo | BX42: 200 | BY42: Media | BZ42: 9a | CB42: 3 | CD42: Organic Home | CE42: Viridiana Covarrubias | CF42: 3310408306 | CH42: organic_home@hotmail.com | CI42: orquídeas | CK42: Efectivo | CL42: 187.5 | CM42: Media | CN42: 4b | CP42: 4
A43: Luna Menstruarte | B43: Karime Hernández | C43: 3317071188 | E43: infolunamenstruarte@gmail.com | F43: Copas menstruales | H43: Efectivo | I43: 750 | J43: Media | K43: 8b | N43: Liliana Jaime | O43: Liliana Gutierrez | P43: 3314103650 | R43: lilianajaime78@gmail.com | U43: Efectivo | V43: 250 | W43: Ninguna | X43: 26a | AA43: Le Ve | AB43: Brenda de la Cruz | AC43: 3312088704 | AE43: bleutulip@hotmail.com | AF43: Quesos y leches veganos de semillas | AG43: Ceci | AH43: Efectivo | AI43: 250 | AJ43: Media | AK43: 17a | AN43: Liliana Jaime | AO43: Liliana Gutierrez | AP43: 3314103650 | AR43: lilianajaime78@gmail.com | AS43: ropa de diseño independiente | AT43: Sofía | AU43: Efectivo | AV43: 200 | AW43: Ninguna | AX43: 34c | AZ43: 1 | BB43: Liliana Jaime | BC43: Liliana Gutierrez | BD43: 3314103650 | BF43: lilianajaime78@gmail.com | BG43: ropa de diseño independiente | BH43: Sofía | BI43: Efectivo | BJ43: 200 | BK43: Ninguna | BL43: 31c | BN43: 2 | BP43: Happy Bakery | BQ43: Adriana Gutierrez Jaime | BR43: 3313386181 | BS43: 33652050 | BT43: adimigo@yahoo.com.mx | BU43: Galletas, donas y brownies | BV43: Sofía | BW43: Efectivo | BX43: 250 | BY43: Media | BZ43: 35b | CA43: N | CB43: 1 | CD43: Pacha Mama | CE43: Lilia Ibarra | CF43: 3333979927 | CG43: 36563118 | CH43: charly-22889@hotmail.com | CI43: Bisutaría y piedras naturales | CJ43: Sofía | CK43: Efectivo | CL43: 200 | CM43: Media | CP43: 2
A44: Mishu | B44: Ella Cornejo | C44: 3314415732 | D44: 36275564 | E44: ella.marina.cornejo@gmail.com | F44: Armonizadores de espacios tejidos. | G44: Sofía | H44: Efectivo | I44: 1000 | J44: Media | K44: 15b | L44: N | N44: Lovely Creations | O44: Luz Mantilla | P44: 3339683396 | R44: itza.barba@hp.com | T44: Cecibel | U44: Efectivo | V44: 400 | W44: Completa | X44: 7 | AA44: Lovely Creations | AB44: Luz Mantilla | AC44: 3339683396 | AE44: itza.barba@hp.com | AH44: Efectivo | AI44: 400 | AJ44: Completa | AK44: 7 | AN44: Lo Escencial de la Vida | AO44: Mary McPherson | AP44: 3333116669 | AQ44: 16557103 | AS44: Aceites esenciales. | AT44: Sofía | AU44: Efectivo | AV44: 250 | AW44: Media | AX44: 32b | AY44: N | AZ44: 1 | BB44: Lucy Cactus Company | BC44: Verónica Gil | BD44: 3311185434 | BF44: veronik339.vg@gmail.com | BG44: macetas de barro pintadas | BI44: Efectivo | BJ44: 187.5 | BK44: Media | BL44: 6a | BN44: 2 | BP44: Jamaitingas | BQ44: Arlene Sánchez | BR44: 3334057358 | BT44: miryana23@hotmail.com | BU44: guisados a base de jamaica | BW44: Efectivo | BX44: 200 | BY44: Media | BZ44: 15a | CB44: 3 | CD44: Perla Negra | CE44: Romina de la Parra | CF44: 3332003097 | CG44: 38103965 | CH44: perlanegra.ventas@hotmail.com | CI44: Arcilla termal volcánica, antifaz térmico de arcilla volcánica, piedra de origen volcánico, jabón artesanal de arcilla volcánica y romero. | CK44: Efectivo | CL44: 187.5 | CM44: Media | CN44: 8a | CP44: 2
A45: Ofelia Pozole | B45: Ana Rosales | D45: 38257028 | E45: quetzallicocone@hotmail.com | F45: Pozole vegetariano | H45: Efectivo | I45: 750 | J45: Media | K45: 10b | N45: Lucy Cactus Company | O45: Verónica Gil | P45: 3311185434 | R45: veronik339.vg@gmail.com | S45: macetas de barro pintadas | T45: Sofía | U45: Efectivo | V45: 200 | W45: Media | X45: 25a | AA45: Lucy Cactus Company | AB45: Verónica Gil | AC45: 3311185434 | AE45: veronik339.vg@gmail.com | AF45: macetas de barro pintadas | AH45: Efectivo | AI45: 187.5 | AJ45: Media | AK45: 6a | AN45: Lucy Cactus Company | AO45: Verónica Gil | AP45: 3311185434 | AR45: veronik339.vg@gmail.com | AS45: macetas de barro pintadas | AU45: Efectivo | AV45: 187.5 | AW45: Media | AX45: 6a | AZ45: 1 | BB45: Minerarte | BC45: Leonardo Dueñas | BD45: 3331878752 | BF45: lfalout26@gmail.com | BG45: lámparas de cuarzo | BH45: Sofía | BI45: Falta | BJ45: 60 | BK45: Media | BN45: 2 | BP45: Klok | BQ45: María Luisa Álvarez Caloca | BR45: 3336777441 | BS45: 38231337 | BT45: maria@xtal.com.mx | BU45: Ilustración a base de primacolor. | BV45: Gonzalo | BW45: Efectivo | BX45: 200 | BY45: Media | BZ45: 25a | CB45: 3 | CD45: Piña Palmera | CE45: Lula de Lara | CF45: 3311900294 | CH45: lula@pinapalmera.com | CI45: aguas naturales de frutas | CJ45: Sofía | CK45: Efectivo | CL45: 187.5 | CM45: Ninguna | CN45: 0 | CP45: 4
A46: Pangourmeti | B46: Mónica Herández | C46: 3314501114 | E46: monica@cosmosmkt.com | F46: Pan y galletas. | H46: Intercambio | I46: 0 | J46: Completa | K46: 4 | N46: Luna Menstruarte | O46: Karime Hernández | P46: 3317071188 | R46: infolunamenstruarte@gmail.com | S46: Copas menstruales | U46: Efectivo | V46: 750 | W46: Media | X46: 8b | AA46: Luna Menstruarte | AB46: Karime Hernández | AC46: 3317071188 | AE46: infolunamenstruarte@gmail.com | AF46: Copas menstruales | AH46: Efectivo | AI46: 187.5 | AJ46: Media | AK46: 9a | AN46: Luna Menstruarte | AO46: Karime Hernández | AP46: 3317071188 | AR46: infolunamenstruarte@gmail.com | AS46: Copas menstruales | AU46: Efectivo | AV46: 187.5 | AW46: Media | AX46: 8a | AZ46: 1 | BB46: Mishu | BC46: Ella Cornejo | BD46: 3314415732 | BE46: 36275564 | BF46: ella.marina.cornejo@gmail.com | BG46: Armonizadores de espacios tejidos. | BH46: Sofía | BI46: Efectivo | BJ46: 200 | BK46: Media | BL46: 15b | BN46: 2 | BP46: La Bee Organic | BQ46: Luis Elizondo | BR46: 3331787364 | BT46: labeeorganic@gmail.com | BU46: bálsamo para labios | BW46: Efectivo | BX46: 200 | BY46: Media | BZ46: 25b | CB46: 2 | CD46: Productos Gourmet | CE46: Victor Hugo Lamas | CF46: 3314112703 | CH46: victorlamasr@yahoo.com.mx | CK46: Efectivo | CL46: 200 | CM46: Media | CN46: 8b | CP46: 3
A47: Perla Negra | B47: Romina de la Parra | C47: 3332003097 | D47: 38103965 | E47: perlanegra.ventas@hotmail.com | F47: Arcilla termal volcánica, antifaz térmico de arcilla volcánica, piedra de origen volcánico, jabón artesanal de arcilla volcánica y romero. | H47: Banco | I47: 187.5 | J47: Media | K47: 6a | N47: Mielomex | O47: Joel Lopez | P47: 3310932686 | R47: karma_22@hotmail.com | U47: Efectivo | V47: 250 | W47: Media | X47: 23b | AA47: Minerarte | AB47: Leonardo Dueñas | AC47: 3331878752 | AE47: lfalout26@gmail.com | AF47: lámparas de cuarzo | AG47: Sofía | AH47: Efectivo | AI47: 200 | AJ47: Media | AK47: 31 | AN47: Lupita de la Peña | AO47: Lupita de la Peña | AP47: 3338099924 | AR47: lupitadelapena@gmail.com | AS47: galletas de avena, brownies y reposteria artesanal | AU47: Efectivo | AV47: 200 | AW47: Media | AX47: 34a | AZ47: 1 | BB47: MontPao | BC47: Rodrigo Juárez Salazar | BD47: 3315508402 | BF47: borrego_gdl@hotmail.com | BG47: Blueberrys, mermeladas. | BH47: Sofía | BI47: Efectivo | BJ47: 187.5 | BK47: Media | BL47: 2a | BN47: 2 | BP47: La Ciudad de los Campos | BQ47: Ángeles Muñoz | BR47: 3335591738 | BT47: mangelesmunoz@me.com | BU47: Quesos, aderezos. | BW47: Efectivo | BX47: 100 | BY47: Media | BZ47: 12a | CB47: 3 | CD47: Promaná | CE47: Manuel Mendez | CF47: 3334488380 | CG47: 36314024 | CH47: jmmu.97@gmail.com | CI47: Huevo orgánico de rancho, moringa. | CK47: Banco | CL47: 187.5 | CM47: Media | CN47: 18b | CP47: 3
A48: Productos Gourmet | B48: Victor Hugo Lamas | C48: 3314112703 | E48: victorlamasr@yahoo.com.mx | H48: Efectivo | I48: 200 | J48: Media | K48: 3b | N48: Milenium | O48: alfonso jimenez | P48: 3315549675 | R48: antiquemilenium@hotmail.com | U48: Efectivo | V48: 500 | W48: Completa | X48: 29 | AA48: Mishu | AB48: Ella Cornejo | AC48: 3314415732 | AD48: 36275564 | AE48: ella.marina.cornejo@gmail.com | AF48: Armonizadores de espacios tejidos. | AG48: Sofía | AH48: Efectivo | AI48: 200 | AJ48: Media | AK48: 15b | AN48: Klok | AO48: María Luisa Álvarez Caloca | AP48: 3336777441 | AQ48: 38231337 | AR48: maria@xtal.com.mx | AS48: Ilustración a base de primacolor. | AT48: Gonzalo | AU48: Efectivo | AV48: 200 | AW48: Media | AX48: 19a | AZ48: 1 | BB48: Nutri Antojos | BC48: Jorge González | BD48: 3335841961 | BF48: nutriantojos@outlook.com | BG48: Fruta y verdura deshidratada, nopal con chile. | BI48: Efectivo | BJ48: 200 | BK48: Media | BL48: 8b | BN48: 2 | BP48: Liliana Jaime | BQ48: Liliana Gutierrez | BR48: 3314103650 | BT48: lilianajaime78@gmail.com | BU48: ropa de diseño independiente | BV48: Sofía | BW48: Efectivo | BX48: 200 | BY48: Ninguna | BZ48: 35c | CB48: 3 | CD48: Quetzalli | CE48: Aura Rodriguez | CF48: 3317711276 | CG48: 3338244746 | CH48: pacoatlicue@hotmail.com | CI48: lámparas, aretes de cupcakes y postres, dijes de resina | CK48: Efectivo | CL48: 187.5 | CM48: Media | CN48: 17a | CP48: 4
A49: Productos Vegetarianos | B49: Zoé Ruelas SantaCruz | C49: 3331406846 | E49: psicozoe@hotmail.com | F49: Chorizo vegetariano, cochinita vegetariana y milanesas de trigo. | G49: Sofía | H49: Efectivo | I49: 250 | J49: Media | K49: 5a | L49: N | N49: Minerales Naturales | O49: Leonardo Dueñas | P49: 3331878752 | U49: Efectivo | V49: 250 | W49: Media | X49: 27b | AA49: MontPao | AB49: Rodrigo Juárez Salazar | AC49: 3315508402 | AE49: borrego_gdl@hotmail.com | AF49: Blueberrys, mermeladas. | AG49: Sofía | AH49: Efectivo | AI49: 250 | AJ49: Media | AK49: 2a | AN49: Minerarte | AO49: Leonardo Dueñas | AP49: 3331878752 | AR49: lfalout26@gmail.com | AS49: lámparas de cuarzo | AT49: Sofía | AU49: Efectivo | AV49: 200 | AW49: Media | AX49: 19b | AZ49: 1 | BB49: Organic Home | BC49: Viridiana Covarrubias | BD49: 3310408306 | BF49: organic_home@hotmail.com | BG49: orquídeas | BI49: Efectivo | BJ49: 187.5 | BK49: Media | BL49: 16a | BN49: 2 | BP49: Lucy Cactus Company | BQ49: Verónica Gil | BR49: 3311185434 | BT49: veronik339.vg@gmail.com | BU49: macetas de barro pintadas | BW49: Efectivo | BX49: 187.5 | BY49: Media | BZ49: 14a | CB49: 3 | CD49: Sagrante | CE49: Luis Felipe Angulo | CF49: 3310640389 | CH49: lufac90@hotmail.com | CI49: Licor de jamaica. | CK49: Efectivo | CL49: 187.5 | CM49: Media | CN49: 12b | CP49: 4
A50: Promaná | B50: Manuel Mendez | C50: 3334488380 | D50: 36314024 | E50: jmmu.97@gmail.com | F50: Huevo orgánico de rancho, moringa. | H50: Banco | I50: 1740 | J50: Completa | K50: 22 | N50: Mishu | O50: Ella Cornejo | P50: 3314415732 | Q50: 36275564 | R50: ella.marina.cornejo@gmail.com | S50: Armonizadores de espacios tejidos. | T50: Sofía | U50: Efectivo | V50: 1000 | W50: Media | X50: 15b | AA50: Piña Palmera | AB50: Lula de Lara | AC50: 3311900294 | AE50: lula@pinapalmera.com | AF50: aguas naturales de frutas | AG50: Sofía | AH50: Efectivo | AI50: 187.5 | AJ50: Media | AK50: 0 | AN50: Mishu | AO50: Ella Cornejo | AP50: 3314415732 | AQ50: 36275564 | AR50: ella.marina.cornejo@gmail.com | AS50: Armonizadores de espacios tejidos. | AT50: Sofía | AU50: Efectivo | AV50: 200 | AW50: Media | AX50: 15 | AZ50: 1 | BB50: Piña Palmera | BC50: Lula de Lara | BD50: 3311900294 | BF50: lula@pinapalmera.com | BG50: aguas naturales de frutas | BH50: Sofía | BI50: Efectivo | BJ50: 187.5 | BK50: Media | BL50: 0 | BN50: 2 | BP50: Luna Menstruarte | BQ50: Karime Hernández | BR50: 3317071188 | BT50: infolunamenstruarte@gmail.com | BU50: Copas menstruales | BW50: Efectivo | BX50: 200 | BY50: Media | BZ50: 18b | CB50: 1 | CD50: Sáname | CE50: Sergio Álvarez | CF50: 3312176844 | CH50: sergio-alvarez61@hotmail.com | CI50: Productos derivados de la miel | CK50: Efectivo | CL50: 187.5 | CM50: Media | CN50: 2b | CP50: 4
A51: Quetzalli | B51: Aura Rodriguez | C51: 3317711276 | D51: 3338244746 | E51: pacoatlicue@hotmail.com | F51: lámparas, aretes de cupcakes y postres, dijes de resina | H51: Efectivo | I51: 750 | J51: Media | K51: 19b | N51: Ofelia Pozole | O51: Ana Rosales | Q51: 38257028 | R51: quetzallicocone@hotmail.com | S51: Pozole vegetariano | U51: Efectivo | V51: 750 | W51: Media | X51: 18a | AA51: Promaná | AB51: Manuel Mendez | AC51: 3334488380 | AD51: 36314024 | AE51: jmmu.97@gmail.com | AF51: Huevo orgánico de rancho, moringa. | AH51: Banco | AI51: 375 | AJ51: Completa | AK51: 22 | AN51: MontPao | AO51: Rodrigo Juárez Salazar | AP51: 3315508402 | AR51: borrego_gdl@hotmail.com | AS51: Blueberrys, mermeladas. | AT51: Sofía | AU51: Efectivo | AV51: 200 | AW51: Media | AX51: 2a | AZ51: 1 | BB51: Productos Gourmet | BC51: Victor Hugo Lamas | BD51: 3314112703 | BF51: victorlamasr@yahoo.com.mx | BI51: Efectivo | BJ51: 200 | BK51: Media | BL51: 22a | BN51: 2 | BP51: Mishu | BQ51: Ella Cornejo | BR51: 3314415732 | BS51: 36275564 | BT51: ella.marina.cornejo@gmail.com | BU51: Armonizadores de espacios tejidos. | BV51: Sofía | BW51: Efectivo | BX51: 187.5 | BY51: Media | BZ51: 15b | CB51: 3 | CD51: Sempiterna | CE51: Eugenia Sánchez | CF51: 3311802665 | CH51: es.t-70@hotmail.com | CI51: Dijes de plata | CK51: Efectivo | CL51: 250 | CM51: Media | CN51: 17b | CP51: 2
A52: Sempiterna | B52: Eugenia Sánchez | C52: 3311802665 | E52: es.t-70@hotmail.com | F52: Dijes de plata | H52: Efectivo | I52: 750 | J52: Media | K52: 6b | N52: Productos Gourmet | O52: Victor Hugo Lamas | P52: 3314112703 | R52: victorlamasr@yahoo.com.mx | U52: Efectivo | V52: 200 | W52: Media | X52: 18b | AA52: Quetzalli | AB52: Aura Rodriguez | AC52: 3317711276 | AD52: 3338244746 | AE52: pacoatlicue@hotmail.com | AF52: lámparas, aretes de cupcakes y postres, dijes de resina | AH52: Efectivo | AI52: 187.5 | AJ52: Media | AK52: 21a | AN52: Nutri Antojos | AO52: Jorge González | AP52: 3335841961 | AR52: nutriantojos@outlook.com | AS52: Fruta y verdura deshidratada, nopal con chile. | AU52: Efectivo | AV52: 200 | AW52: Media | AX52: 33a | AZ52: 1 | BB52: Promaná | BC52: Manuel Mendez | BD52: 3334488380 | BE52: 36314024 | BF52: jmmu.97@gmail.com | BG52: Huevo orgánico de rancho, moringa. | BI52: Banco | BJ52: 187.5 | BK52: Media | BL52: 22b | BN52: 2 | BP52: MontPao | BQ52: Rodrigo Juárez Salazar | BR52: 3315508402 | BT52: borrego_gdl@hotmail.com | BU52: Blueberrys, mermeladas. | BV52: Sofía | BW52: Efectivo | BX52: 187.5 | BY52: Media | BZ52: 8a | CB52: 3 | CD52: Sufiz | CE52: Maye Betancourt | CF52: 3317109196 | CG52: 15967909 | CH52: mayedapa@hotmail.com | CI52: palanquetas, granola | CK52: Efectivo | CL52: 190 | CM52: Media | CN52: 18a | CP52: 4
A53: Sufiz | B53: Maye Betancourt | C53: 3317109196 | D53: 15967909 | E53: mayedapa@hotmail.com | F53: palanquetas, granola | H53: Efectivo | I53: 750 | J53: Media | K53: 16b | N53: Promaná | O53: Manuel Mendez | P53: 3334488380 | Q53: 36314024 | R53: jmmu.97@gmail.com | S53: Huevo orgánico de rancho, moringa. | U53: Banco | V53: 1740 | W53: Completa | X53: 20 | AA53: Sagrante | AB53: Luis Felipe Angulo | AC53: 3310640389 | AE53: lufac90@hotmail.com | AF53: Licor de jamaica. | AH53: Efectivo | AI53: 187.5 | AJ53: Media | AK53: 14b | AN53: Organic Home | AO53: Viridiana Covarrubias | AP53: 3310408306 | AR53: organic_home@hotmail.com | AS53: orquídeas | AU53: Efectivo | AV53: 187.5 | AW53: Media | AX53: 16a | AZ53: 1 | BB53: Quetzalli | BC53: Aura Rodriguez | BD53: 3317711276 | BE53: 3338244746 | BF53: pacoatlicue@hotmail.com | BG53: lámparas, aretes de cupcakes y postres, dijes de resina | BI53: Efectivo | BJ53: 187.5 | BK53: Media | BL53: 21a | BN53: 2 | BP53: Nutri Antojos | BQ53: Jorge González | BR53: 3335841961 | BT53: nutriantojos@outlook.com | BU53: Fruta y verdura deshidratada, nopal con chile. | BW53: Efectivo | BX53: 200 | BY53: Media | BZ53: 22b | CB53: 3 | CD53: Vihanta Natura | CE53: Valentina Bontempi | CF53: 3315398142 | CH53: bvale_81@yahoo.it | CI53: cremas a base de extractos y aceites naturales | CK53: Efectivo | CL53: 200 | CM53: Media | CN53: 16b | CP53: 4
A54: Tochtli | B54: Adrián Gutiérrez | C54: 3317440064 | E54: tochtli_desodorante@hotmail.com | F54: Talco desodorante, desodorante rolo, desodorante spray, shampoo, crema para afeitar, pasta de dientes, talco para pies. | I54: 200 | J54: Media | K54: 8a | N54: Quetzalli | O54: Aura Rodriguez | P54: 3317711276 | Q54: 3338244746 | R54: pacoatlicue@hotmail.com | S54: lámparas, aretes de cupcakes y postres, dijes de resina | U54: Efectivo | V54: 750 | W54: Media | X54: 21a | AA54: Sáname | AB54: Sergio Álvarez | AC54: 3312176844 | AE54: sergio-alvarez61@hotmail.com | AF54: Productos derivados de la miel | AH54: Efectivo | AI54: 250 | AJ54: Media | AK54: 2b | AN54: Piña Palmera | AO54: Lula de Lara | AP54: 3311900294 | AR54: lula@pinapalmera.com | AS54: aguas naturales de frutas | AT54: Sofía | AU54: Efectivo | AV54: 187.5 | AW54: Media | AX54: 0b | AZ54: 1 | BB54: Sagrante | BC54: Luis Felipe Angulo | BD54: 3310640389 | BF54: lufac90@hotmail.com | BG54: Licor de jamaica. | BI54: Efectivo | BJ54: 187.5 | BK54: Media | BL54: 20b | BN54: 2 | BP54: Oilstrich | BQ54: Sergio Curiel | BR54: 3315207707 | BS54: 18155093 | BT54: oilstrichproducts@gmail.com | BU54: cremas a base de avestruz | BW54: Falta | BX54: 0 | BY54: Media | BZ54: 34a | CD54: Yerba Sana | CE54: Julieta Hernández | CF54: 3310849639 | CG54: 36470293 | CH54: yerbasana@hotmail.com | CI54: Chía, aceite de coco, sal orgánica. | CK54: Efectivo | CL54: 125 | CM54: Media | CN54: 14a | CP54: 4
A55: Vihanta Natura | B55: Valentina Bontempi | C55: 3315398142 | E55: bvale_81@yahoo.it | F55: cremas a base de extractos y aceites naturales | H55: Efectivo | I55: 750 | J55: Media | K55: 11b | N55: Sáname | O55: Sergio Álvarez | P55: 3312176844 | R55: sergio-alvarez61@hotmail.com | U55: Efectivo | V55: 500 | W55: Completa | X55: 4 | AA55: Sufiz | AB55: Maye Betancourt | AC55: 3317109196 | AD55: 15967909 | AE55: mayedapa@hotmail.com | AF55: palanquetas, granola | AH55: Efectivo | AI55: 187.5 | AJ55: Media | AK55: 19b | AN55: Productos Gourmet | AO55: Victor Hugo Lamas | AP55: 3314112703 | AR55: victorlamasr@yahoo.com.mx | AU55: Efectivo | AV55: 200 | AW55: Media | AX55: 21a | AZ55: 1 | BB55: Sáname | BC55: Sergio Álvarez | BD55: 3312176844 | BF55: sergio-alvarez61@hotmail.com | BG55: Productos derivados de la miel | BI55: Efectivo | BJ55: 187.5 | BK55: Media | BL55: 2b | BN55: 2 | BP55: Organic Home | BQ55: Viridiana Covarrubias | BR55: 3310408306 | BT55: organic_home@hotmail.com | BU55: orquídeas | BW55: Efectivo | BX55: 187.5 | BY55: Media | BZ55: 23a | CB55: 3
A56: Virgo | B56: Victor Ortega | C56: 3314117605 | D56: 38134694 | E56: virgonutricion@hotmail.com | F56: Mermeladas, yoghurt. | H56: Efectivo | I56: 200 | J56: Media | K56: 20b | N56: Sufiz | O56: Maye Betancourt | P56: 3317109196 | Q56: 15967909 | R56: mayedapa@hotmail.com | S56: palanquetas, granola | U56: Efectivo | V56: 750 | W56: Media | X56: 26b | AA56: Vihanta Natura | AB56: Valentina Bontempi | AC56: 3315398142 | AE56: bvale_81@yahoo.it | AF56: cremas a base de extractos y aceites naturales | AH56: Efectivo | AI56: 187.5 | AJ56: Media | AK56: 18a | AN56: Promaná | AO56: Manuel Mendez | AP56: 3334488380 | AQ56: 36314024 | AR56: jmmu.97@gmail.com | AS56: Huevo orgánico de rancho, moringa. | AU56: Banco | AV56: 375 | AW56: Completa | AX56: 22 | AZ56: 1 | BB56: Sempiterna | BC56: Eugenia Sánchez | BD56: 3311802665 | BF56: es.t-70@hotmail.com | BG56: Dijes de plata | BI56: Efectivo | BJ56: 250 | BK56: Media | BL56: 18a | BN56: 1 | BP56: Pacha Mama | BQ56: Lilia Ibarra | BR56: 3333979927 | BS56: 36563118 | BT56: charly-22889@hotmail.com | BU56: Bisutaría y piedras naturales | BV56: Sofía | BW56: Efectivo | BX56: 250 | BY56: Media | BZ56: 32a | CA56: N | CB56: 1
N57: Té de Campo | O57: Karen Soriano | P57: 3310234402 | R57: sorianokrn@gmail.com | S57: Almohadillas con semillas, tizanas, tés. | T57: Cecibel | U57: Efectivo | V57: 250 | W57: Media | X57: 16a | AA57: Yerba Sana | AB57: Julieta Hernández | AC57: 3310849639 | AD57: 36470293 | AE57: yerbasana@hotmail.com | AF57: Chía, aceite de coco, sal orgánica. | AH57: Efectivo | AI57: 125 | AJ57: Media | AK57: 13a | AN57: Quetzalli | AO57: Aura Rodriguez | AP57: 3317711276 | AQ57: 3338244746 | AR57: pacoatlicue@hotmail.com | AS57: lámparas, aretes de cupcakes y postres, dijes de resina | AU57: Efectivo | AV57: 187.5 | AW57: Media | AX57: 20a | AZ57: 1 | BB57: Sufiz | BC57: Maye Betancourt | BD57: 3317109196 | BE57: 15967909 | BF57: mayedapa@hotmail.com | BG57: palanquetas, granola | BI57: Efectivo | BJ57: 190 | BK57: Media | BL57: 31b | BN57: 2 | BP57: Pan Valentina | BQ57: Cristina Araiza Cervantes | BR57: 3312932081 | BT57: an.araizacervantes@gmail.com | BU57: Pan de caja, baguette, bagels. | BV57: Sofía | BW57: Efectivo | BX57: 200 | BY57: Media | BZ57: 12b | CA57: N | CB57: 1
N58: Tishas 4U | O58: Alejandra Hernández | P58: 3333498818 | R58: edelvi2002@hotmail.com | S58: playeras de diseño | T58: Sofía | U58: pendiente | V58: 200 | W58: Media | X58: 25b | AN58: Sagrante | AO58: Luis Felipe Angulo | AP58: 3310640389 | AR58: lufac90@hotmail.com | AS58: Licor de jamaica. | AU58: Efectivo | AV58: 187.5 | AW58: Media | AX58: 21b | AZ58: 1 | BB58: Tochtli | BC58: Adrián Gutiérrez | BD58: 3317440064 | BF58: tochtli_desodorante@hotmail.com | BG58: Talco desodorante, desodorante rolo, desodorante spray, shampoo, crema para afeitar, pasta de dientes, talco para pies. | BI58: Efectivo | BJ58: 200 | BK58: Media | BL58: 8a | BN58: 2 | BP58: Perla Negra | BQ58: Romina de la Parra | BR58: 3332003097 | BS58: 38103965 | BT58: perlanegra.ventas@hotmail.com | BU58: Arcilla termal volcánica, antifaz térmico de arcilla volcánica, piedra de origen volcánico, jabón artesanal de arcilla volcánica y romero. | BW58: Efectivo | BX58: 187.5 | BY58: Media | BZ58: 33b | CB58: 1
N59: Tochtli | O59: Adrián Gutiérrez | P59: 3317440064 | R59: tochtli_desodorante@hotmail.com | S59: Talco desodorante, desodorante rolo, desodorante spray, shampoo, crema para afeitar, pasta de dientes, talco para pies. | T59: Sofía | U59: Efectivo | V59: 200 | W59: Media | X59: 8a | AN59: Sáname | AO59: Sergio Álvarez | AP59: 3312176844 | AR59: sergio-alvarez61@hotmail.com | AS59: Productos derivados de la miel | AU59: Efectivo | AV59: 187.5 | AW59: Media | AX59: 2b | AZ59: 1 | BB59: Vihanta Natura | BC59: Valentina Bontempi | BD59: 3315398142 | BF59: bvale_81@yahoo.it | BG59: cremas a base de extractos y aceites naturales | BI59: Efectivo | BJ59: 200 | BK59: Media | BL59: 18b | BN59: 2 | BP59: Piña Palmera | BQ59: Lula de Lara | BR59: 3311900294 | BT59: lula@pinapalmera.com | BU59: aguas naturales de frutas | BV59: Sofía | BW59: Efectivo | BX59: 187.5 | BY59: Completa | BZ59: 7 | CB59: 3
N60: Vihanta Natura | O60: Valentina Bontempi | P60: 3315398142 | R60: bvale_81@yahoo.it | S60: cremas a base de extractos y aceites naturales | U60: Efectivo | V60: 750 | W60: Media | X60: 19b | AN60: Sufiz | AO60: Maye Betancourt | AP60: 3317109196 | AQ60: 15967909 | AR60: mayedapa@hotmail.com | AS60: palanquetas, granola | AU60: Efectivo | AV60: 187.5 | AW60: Media | AX60: 30b | AZ60: 1 | BB60: Yerba Sana | BC60: Julieta Hernández | BD60: 3310849639 | BE60: 36470293 | BF60: yerbasana@hotmail.com | BG60: Chía, aceite de coco, sal orgánica. | BI60: Efectivo | BJ60: 125 | BK60: Media | BL60: 14a | BN60: 2 | BP60: Quetzalli | BQ60: Aura Rodriguez | BR60: 3317711276 | BS60: 3338244746 | BT60: pacoatlicue@hotmail.com | BU60: lámparas, aretes de cupcakes y postres, dijes de resina | BW60: Efectivo | BX60: 187.5 | BY60: Media | BZ60: 21a | CB60: 3
N61: Piña Palmera | O61: Lula de Lara | P61: 3311900294 | R61: lula@pinapalmera.com | S61: aguas naturales de frutas | U61: Efectivo | V61: 250 | W61: Ninguna | AN61: Tochtli | AO61: Adrián Gutiérrez | AP61: 3317440064 | AR61: tochtli_desodorante@hotmail.com | AS61: Talco desodorante, desodorante rolo, desodorante spray, shampoo, crema para afeitar, pasta de dientes, talco para pies. | AU61: Efectivo | AV61: 200 | AW61: Media | AX61: 8b | AZ61: 1 | BP61: Sagrante | BQ61: Luis Felipe Angulo | BR61: 3310640389 | BT61: lufac90@hotmail.com | BU61: Licor de jamaica. | BW61: Efectivo | BX61: 187.5 | BY61: Media | BZ61: 28a | CB61: 3
N62: Sagrante | O62: Luis Felipe Angulo | P62: 3310640389 | R62: lufac90@hotmail.com | S62: Licor de jamaica. | U62: Efectivo | V62: 187.5 | W62: Media | AN62: Vihanta Natura | AO62: Valentina Bontempi | AP62: 3315398142 | AR62: bvale_81@yahoo.it | AS62: cremas a base de extractos y aceites naturales | AU62: Efectivo | AV62: 187.5 | AW62: Media | AX62: 18a | AZ62: 1 | BP62: Sáname | BQ62: Sergio Álvarez | BR62: 3312176844 | BT62: sergio-alvarez61@hotmail.com | BU62: Productos derivados de la miel | BW62: Efectivo | BX62: 187.5 | BY62: Media | BZ62: 8b | CB62: 3
AN63: Yerba Sana | AO63: Julieta Hernández | AP63: 3310849639 | AQ63: 36470293 | AR63: yerbasana@hotmail.com | AS63: Chía, aceite de coco, sal orgánica. | AU63: Efectivo | AV63: 125 | AW63: Media | AX63: 33b | AZ63: 1 | BP63: Sufiz | BQ63: Maye Betancourt | BR63: 3317109196 | BS63: 15967909 | BT63: mayedapa@hotmail.com | BU63: palanquetas, granola | BW63: Efectivo | BX63: 180 | BY63: Media | BZ63: 26b | CB63: 3
BP64: Tempera 32o | BQ64: Silvia Zúñiga | BR64: 3310795109 | BT64: tempera32grados@gmail.com | BU64: Chocolate | BW64: Efectivo | BX64: 200 | BY64: Media | BZ64: 26a | CB64: 1
BP65: Tlatoani | BQ65: Gema López Méndez | BR65: 3316013744 | BS65: 38232703 | BT65: lupituxel@hotmail.com | BU65: ropa de diseño independiente | BV65: Sofía | BW65: Efectivo | BX65: 187.5 | BY65: Media | BZ65: 33a | CA65: N | CB65: 1
BP66: Tochtli | BQ66: Adrián Gutiérrez | BR66: 3317440064 | BT66: tochtli_desodorante@hotmail.com | BU66: Talco desodorante, desodorante rolo, desodorante spray, shampoo, crema para afeitar, pasta de dientes, talco para pies. | BW66: Efectivo | BX66: 200 | BY66: Media | BZ66: 18a | CB66: 3
BP67: Vihanta Natura | BQ67: Valentina Bontempi | BR67: 3315398142 | BT67: bvale_81@yahoo.it | BU67: cremas a base de extractos y aceites naturales | BW67: Efectivo | BX67: 200 | BY67: Media | BZ67: 24a | CB67: 3
BP68: Yerba Sana | BQ68: Julieta Hernández | BR68: 3310849639 | BS68: 36470293 | BT68: yerbasana@hotmail.com | BU68: Chía, aceite de coco, sal orgánica. | BW68: Efectivo | BX68: 125 | BY68: Media | BZ68: 22a | CB68: 3

Sheet Hoja2

Sheet Reclamo de equipaje rediseñado
A1: # Vuelo | B1: LÍNEA AÉREA | C1: HORA AERONAVE POSICIÓN | D1: HORA PRIMER MALETA | E1: Tiempo | F1: HORA ÚLTIMA MALETA | G1: Tiempo2 | H1: FECHA | I1: Procedencia | J1: Equipo | K1: Capacidad | L1: Nacional/ Internacional | M1: Mes
A2: 8851 | B2: =VLOOKUP(Tabla6[[#This Row],['# Vuelo]],'Validacion reclamo de equipaje'!P:Q,2,0) -> MEXICO AEREO | C2: 0.87152778 | D2: 0.91111111 | E2: ='Reclamo de equipaje rediseñado'!$D2-'Reclamo de equipaje rediseñado'!$C2 -> 0.039583333 | F2: 0.91666667 | G2: =F2-D2 -> 0.0055555556 | H2: 41721 | I2: MEX | J2: ER4 | K2: =VLOOKUP(J2,'Validacion reclamo de equipaje'!L:M,2,0) -> 50 | L2: =VLOOKUP(I2,'Validacion reclamo de equipaje'!H:I,2,0) -> Nacional | M2: Marzo
A3: 8702 | B3: =VLOOKUP(Tabla6[[#This Row],['# Vuelo]],'Validacion reclamo de equipaje'!P:Q,2,0) -> MEXICO AEREO | C3: 0.63402778 | D3: 0.64027778 | E3: ='Reclamo de equipaje rediseñado'!$D3-'Reclamo de equipaje rediseñado'!$C3 -> 0.00625 | F3: 0.64861111 | G3: =F3-D3 -> 0.0083333333 | H3: 41725 | I3: QRO | J3: ER4 | K3: =VLOOKUP(J3,'Validacion reclamo de equipaje'!L:M,2,0) -> 50 | L3: =VLOOKUP(I3,'Validacion reclamo de equipaje'!H:I,2,0) -> Nacional | M3: Marzo
A4: 3120 | B4: =VLOOKUP(Tabla6[[#This Row],['# Vuelo]],'Validacion reclamo de equipaje'!P:Q,2,0) -> MEXICO AEREO | C4: 0.44027778 | D4: 0.44791667 | E4: ='Reclamo de equipaje rediseñado'!$D4-'Reclamo de equipaje rediseñado'!$C4 -> 0.0076388889 | F4: 0.45208333 | G4: =F4-D4 -> 0.0041666667 | H4: 41726 | I4: QRO | J4: No encontrado, probable error | K4: =VLOOKUP(J4,'Validacion reclamo de equipaje'!L:M,2,0) -> #N/A | L4: =VLOOKUP(I4,'Validacion reclamo de equipaje'!H:I,2,0) -> Nacional | M4: Marzo
A5: 2811 | B5: =VLOOKUP(Tabla6[[#This Row],['# Vuelo]],'Validacion reclamo de equipaje'!P:Q,2,0) -> MEXICO AEREO | C5: 0.59583333 | D5: 0.59861111 | E5: ='Reclamo de equipaje rediseñado'!$D5-'Reclamo de equipaje rediseñado'!$C5 -> 0.0027777778 | F5: 0.60416667 | G5: =F5-D5 -> 0.0055555556 | H5: 41722 | I5: QRO | J5: No encontrado, probable error | K5: =VLOOKUP(J5,'Validacion reclamo de equipaje'!L:M,2,0) -> #N/A | L5: =VLOOKUP(I5,'Validacion reclamo de equipaje'!H:I,2,0) -> Nacional | M5: Marzo
A6: 2625 | B6: =VLOOKUP(Tabla6[[#This Row],['# Vuelo]],'Validacion reclamo de equipaje'!P:Q,2,0) -> MEXICO AEREO | C6: 0.86666667 | D6: 0.875 | E6: ='Reclamo de equipaje rediseñado'!$D6-'Reclamo de equipaje rediseñado'!$C6 -> 0.0083333333 | F6: 0.87708333 | G6: =F6-D6 -> 0.0020833333 | H6: 41715 | I6: TLC | J6: ER4 | K6: =VLOOKUP(J6,'Validacion reclamo de equipaje'!L:M,2,0) -> 50 | L6: =VLOOKUP(I6,'Validacion reclamo de equipaje'!H:I,2,0) -> Nacional | M6: Marzo
A7: 2625 | B7: =VLOOKUP(Tabla6[[#This Row],['# Vuelo]],'Validacion reclamo de equipaje'!P:Q,2,0) -> MEXICO AEREO | C7: 0.86597222 | D7: 0.87361111 | E7: ='Reclamo de equipaje rediseñado'!$D7-'Reclamo de equipaje rediseñado'!$C7 -> 0.0076388889 | F7: 0.87847222 | G7: =F7-D7 -> 0.0048611111 | H7: 41719 | I7: TLC | J7: ER4 | K7: =VLOOKUP(J7,'Validacion reclamo de equipaje'!L:M,2,0) -> 50 | L7: =VLOOKUP(I7,'Validacion reclamo de equipaje'!H:I,2,0) -> Nacional | M7: Marzo
A8: 2625 | B8: =VLOOKUP(Tabla6[[#This Row],['# Vuelo]],'Validacion reclamo de equipaje'!P:Q,2,0) -> MEXICO AEREO | C8: 0.85416667 | D8: 0.85902778 | E8: ='Reclamo de equipaje rediseñado'!$D8-'Reclamo de equipaje rediseñado'!$C8 -> 0.0048611111 | F8: 0.86180556 | G8: =F8-D8 -> 0.0027777778 | H8: 41723 | I8: TLC | J8: ER4 | K8: =VLOOKUP(J8,'Validacion reclamo de equipaje'!L:M,2,0) -> 50 | L8: =VLOOKUP(I8,'Validacion reclamo de equipaje'!H:I,2,0) -> Nacional | M8: Marzo
A9: 2625 | B9: =VLOOKUP(Tabla6[[#This Row],['# Vuelo]],'Validacion reclamo de equipaje'!P:Q,2,0) -> MEXICO AEREO | C9: 0.87847222 | D9: 0.88333333 | E9: ='Reclamo de equipaje rediseñado'!$D9-'Reclamo de equipaje rediseñado'!$C9 -> 0.0048611111 | F9: 0.88611111 | G9: =F9-D9 -> 0.0027777778 | H9: 41724 | I9: TLC | J9: ER4 | K9: =VLOOKUP(J9,'Validacion reclamo de equipaje'!L:M,2,0) -> 50 | L9: =VLOOKUP(I9,'Validacion reclamo de equipaje'!H:I,2,0) -> Nacional | M9: Marzo
A10: 2625 | B10: =VLOOKUP(Tabla6[[#This Row],['# Vuelo]],'Validacion reclamo de equipaje'!P:Q,2,0) -> MEXICO AEREO | C10: 0.85277778 | D10: 0.86111111 | E10: ='Reclamo de equipaje rediseñado'!$D10-'Reclamo de equipaje rediseñado'!$C10 -> 0.0083333333 | F10: 0.86666667 | G10: =F10-D10 -> 0.0055555556 | H10: 41724 | I10: TLC | J10: ER4 | K10: =VLOOKUP(J10,'Validacion reclamo de equipaje'!L:M,2,0) -> 50 | L10: =VLOOKUP(I10,'Validacion reclamo de equipaje'!H:I,2,0) -> Nacional | M10: Marzo
A11: 2625 | B11: =VLOOKUP(Tabla6[[#This Row],['# Vuelo]],'Validacion reclamo de equipaje'!P:Q,2,0) -> MEXICO AEREO | C11: 0.85902778 | D11: 0.86805556 | E11: ='Reclamo de equipaje rediseñado'!$D11-'Reclamo de equipaje rediseñado'!$C11 -> 0.0090277778 | F11: 0.87152778 | G11: =F11-D11 -> 0.0034722222 | H11: 41725 | I11: TLC | J11: ER4 | K11: =VLOOKUP(J11,'Validacion reclamo de equipaje'!L:M,2,0) -> 50 | L11: =VLOOKUP(I11,'Validacion reclamo de equipaje'!H:I,2,0) -> Nacional | M11: Marzo
A12: 2625 | B12: =VLOOKUP(Tabla6[[#This Row],['# Vuelo]],'Validacion reclamo de equipaje'!P:Q,2,0) -> MEXICO AEREO | C12: 0.91388889 | D12: 0.92083333 | E12: ='Reclamo de equipaje rediseñado'!$D12-'Reclamo de equipaje rediseñado'!$C12 -> 0.0069444444 | F12: 0.92291667 | G12: =F12-D12 -> 0.0020833333 | H12: 41726 | I12: TLC | J12: ER4 | K12: =VLOOKUP(J12,'Validacion reclamo de equipaje'!L:M,2,0) -> 50 | L12: =VLOOKUP(I12,'Validacion reclamo de equipaje'!H:I,2,0) -> Nacional | M12: Marzo
A13: 2622 | B13: =VLOOKUP(Tabla6[[#This Row],['# Vuelo]],'Validacion reclamo de equipaje'!P:Q,2,0) -> MEXICO AEREO | C13: 0.45486111 | D13: 0.45902778 | E13: ='Reclamo de equipaje rediseñado'!$D13-'Reclamo de equipaje rediseñado'!$C13 -> 0.0041666667 | F13: 0.46111111 | G13: =F13-D13 -> 0.0020833333 | H13: 41714 | I13: HMO | J13: ER4 | K13: =VLOOKUP(J13,'Validacion reclamo de equipaje'!L:M,2,0) -> 50 | L13: =VLOOKUP(I13,'Validacion reclamo de equipaje'!H:I,2,0) -> Nacional | M13: Marzo
... A213: 1114 | B213: =VLOOKUP(Tabla6[[#This Row],['# Vuelo]],'Validacion reclamo de equipaje'!P:Q,2,0) -> MEXICO AEREO | C213: 0.88333333 | D213: 0.88680556 | E213: ='Reclamo de equipaje rediseñado'!$D213-'Reclamo de equipaje rediseñado'!$C213 -> 0.0034722222 | F213: 0.89305556 | G213: =F213-D213 -> 0.00625 | H213: 41724 | I213: MEX | J213: B737-800 | K213: =VLOOKUP(J213,'Validacion reclamo de equipaje'!L:M,2,0) -> 189 | L213: =VLOOKUP(I213,'Validacion reclamo de equipaje'!H:I,2,0) -> Nacional | M213: Marzo
A214: L | B214: =VLOOKUP(Tabla6[[#This Row],['# Vuelo]],'Validacion reclamo de equipaje'!P:Q,2,0) -> MEXICO AEREO | C214: 0.88611111 | D214: 0.89097222 | E214: ='Reclamo de equipaje rediseñado'!$D214-'Reclamo de equipaje rediseñado'!$C214 -> 0.0048611111 | F214: 0.90069444 | G214: =F214-D214 -> 0.0097222222 | H214: 41721 | I214: MEX | J214: No encontrado, probable error | K214: =VLOOKUP(J214,'Validacion reclamo de equipaje'!L:M,2,0) -> #N/A | L214: =VLOOKUP(I214,'Validacion reclamo de equipaje'!H:I,2,0) -> Nacional | M214: Marzo
A215: 785 | B215: =VLOOKUP(Tabla6[[#This Row],['# Vuelo]],'Validacion reclamo de equipaje'!P:Q,2,0) -> MEXICO AEREO | C215: 0.21597222 | D215: 0.23263889 | E215: ='Reclamo de equipaje rediseñado'!$D215-'Reclamo de equipaje rediseñado'!$C215 -> 0.016666667 | F215: 0.24930556 | G215: =F215-D215 -> 0.016666667 | H215: 41713 | I215: LAX | J215: B737-800 | K215: =VLOOKUP(J215,'Validacion reclamo de equipaje'!L:M,2,0) -> 189 | L215: =VLOOKUP(I215,'Validacion reclamo de equipaje'!H:I,2,0) -> Internacional | M215: Marzo
A216: 785 | B216: =VLOOKUP(Tabla6[[#This Row],['# Vuelo]],'Validacion reclamo de equipaje'!P:Q,2,0) -> MEXICO AEREO | C216: 0.21666667 | D216: 0.22638889 | E216: ='Reclamo de equipaje rediseñado'!$D216-'Reclamo de equipaje rediseñado'!$C216 -> 0.0097222222 | F216: 0.24097222 | G216: =F216-D216 -> 0.014583333 | H216: 41715 | I216: LAX | J216: B737-800 | K216: =VLOOKUP(J216,'Validacion reclamo de equipaje'!L:M,2,0) -> 189 | L216: =VLOOKUP(I216,'Validacion reclamo de equipaje'!H:I,2,0) -> Internacional | M216: Marzo
A217: 785 | B217: =VLOOKUP(Tabla6[[#This Row],['# Vuelo]],'Validacion reclamo de equipaje'!P:Q,2,0) -> MEXICO AEREO | C217: 0.22430556 | D217: 0.22569444 | E217: ='Reclamo de equipaje rediseñado'!$D217-'Reclamo de equipaje rediseñado'!$C217 -> 0.0013888889 | F217: 0.25 | G217: =F217-D217 -> 0.024305556 | H217: 41716 | I217: LAX | J217: B737-800 | K217: =VLOOKUP(J217,'Validacion reclamo de equipaje'!L:M,2,0) -> 189 | L217: =VLOOKUP(I217,'Validacion reclamo de equipaje'!H:I,2,0) -> Internacional | M217: Marzo
A218: 785 | B218: =VLOOKUP(Tabla6[[#This Row],['# Vuelo]],'Validacion reclamo de equipaje'!P:Q,2,0) -> MEXICO AEREO | C218: 0.16875 | D218: 0.2125 | E218: ='Reclamo de equipaje rediseñado'!$D218-'Reclamo de equipaje rediseñado'!$C218 -> 0.04375 | F218: 0.23958333 | G218: =F218-D218 -> 0.027083333 | H218: 41717 | I218: LAX | J218: B737-800 | K218: =VLOOKUP(J218,'Validacion reclamo de equipaje'!L:M,2,0) -> 189 | L218: =VLOOKUP(I218,'Validacion reclamo de equipaje'!H:I,2,0) -> Internacional | M218: Marzo
A219: 785 | B219: =VLOOKUP(Tabla6[[#This Row],['# Vuelo]],'Validacion reclamo de equipaje'!P:Q,2,0) -> MEXICO AEREO | C219: 0.20694444 | D219: 0.21388889 | E219: ='Reclamo de equipaje rediseñado'!$D219-'Reclamo de equipaje rediseñado'!$C219 -> 0.0069444444 | F219: 0.22430556 | G219: =F219-D219 -> 0.010416667 | H219: 41719 | I219: LAX | J219: B737-800 | K219: =VLOOKUP(J219,'Validacion reclamo de equipaje'!L:M,2,0) -> 189 | L219: =VLOOKUP(I219,'Validacion reclamo de equipaje'!H:I,2,0) -> Internacional | M219: Marzo
A220: 785 | B220: =VLOOKUP(Tabla6[[#This Row],['# Vuelo]],'Validacion reclamo de equipaje'!P:Q,2,0) -> MEXICO AEREO | C220: 0.20625 | D220: 0.21944444 | E220: ='Reclamo de equipaje rediseñado'!$D220-'Reclamo de equipaje rediseñado'!$C220 -> 0.013194444 | F220: 0.25138889 | G220: =F220-D220 -> 0.031944444 | H220: 41719 | I220: LAX | J220: B737-800 | K220: =VLOOKUP(J220,'Validacion reclamo de equipaje'!L:M,2,0) -> 189 | L220: =VLOOKUP(I220,'Validacion reclamo de equipaje'!H:I,2,0) -> Internacional | M220: Marzo
A221: 785 | B221: =VLOOKUP(Tabla6[[#This Row],['# Vuelo]],'Validacion reclamo de equipaje'!P:Q,2,0) -> MEXICO AEREO | C221: 0.21111111 | D221: 0.22361111 | E221: ='Reclamo de equipaje rediseñado'!$D221-'Reclamo de equipaje rediseñado'!$C221 -> 0.0125 | F221: 0.24583333 | G221: =F221-D221 -> 0.022222222 | H221: 41721 | I221: LAX | J221: B737-800 | K221: =VLOOKUP(J221,'Validacion reclamo de equipaje'!L:M,2,0) -> 189 | L221: =VLOOKUP(I221,'Validacion reclamo de equipaje'!H:I,2,0) -> Internacional | M221: Marzo
A222: 785 | B222: =VLOOKUP(Tabla6[[#This Row],['# Vuelo]],'Validacion reclamo de equipaje'!P:Q,2,0) -> MEXICO AEREO | C222: 0.20902778 | D222: 0.21944444 | E222: ='Reclamo de equipaje rediseñado'!$D222-'Reclamo de equipaje rediseñado'!$C222 -> 0.010416667 | F222: 0.24861111 | G222: =F222-D222 -> 0.029166667 | H222: 41721 | I222: LAX | J222: B737-800 | K222: =VLOOKUP(J222,'Validacion reclamo de equipaje'!L:M,2,0) -> 189 | L222: =VLOOKUP(I222,'Validacion reclamo de equipaje'!H:I,2,0) -> Internacional | M222: Marzo
A223: 785 | B223: =VLOOKUP(Tabla6[[#This Row],['# Vuelo]],'Validacion reclamo de equipaje'!P:Q,2,0) -> MEXICO AEREO | C223: 0.25416667 | D223: 0.26319444 | E223: ='Reclamo de equipaje rediseñado'!$D223-'Reclamo de equipaje rediseñado'!$C223 -> 0.0090277778 | F223: 0.275 | G223: =F223-D223 -> 0.011805556 | H223: 41723 | I223: LAX | J223: B737-800 | K223: =VLOOKUP(J223,'Validacion reclamo de equipaje'!L:M,2,0) -> 189 | L223: =VLOOKUP(I223,'Validacion reclamo de equipaje'!H:I,2,0) -> Internacional | M223: Marzo
A224: 785 | B224: =VLOOKUP(Tabla6[[#This Row],['# Vuelo]],'Validacion reclamo de equipaje'!P:Q,2,0) -> MEXICO AEREO | C224: 0.19652778 | D224: 0.20416667 | E224: ='Reclamo de equipaje rediseñado'!$D224-'Reclamo de equipaje rediseñado'!$C224 -> 0.0076388889 | F224: 0.23541667 | G224: =F224-D224 -> 0.03125 | H224: 41724 | I224: LAX | J224: B737-800 | K224: =VLOOKUP(J224,'Validacion reclamo de equipaje'!L:M,2,0) -> 189 | L224: =VLOOKUP(I224,'Validacion reclamo de equipaje'!H:I,2,0) -> Internacional | M224: Marzo
A225: 785 | B225: =VLOOKUP(Tabla6[[#This Row],['# Vuelo]],'Validacion reclamo de equipaje'!P:Q,2,0) -> MEXICO AEREO | C225: 0.20763889 | D225: 0.22083333 | E225: ='Reclamo de equipaje rediseñado'!$D225-'Reclamo de equipaje rediseñado'!$C225 -> 0.013194444 | F225: 0.25486111 | G225: =F225-D225 -> 0.034027778 | H225: 41724 | I225: LAX | J225: B737-800 | K225: =VLOOKUP(J225,'Validacion reclamo de equipaje'!L:M,2,0) -> 189 | L225: =VLOOKUP(I225,'Validacion reclamo de equipaje'!H:I,2,0) -> Internacional | M225: Marzo
A226: 785 | B226: =VLOOKUP(Tabla6[[#This Row],['# Vuelo]],'Validacion reclamo de equipaje'!P:Q,2,0) -> MEXICO AEREO | C226: 0.21458333 | D226: 0.22569444 | E226: ='Reclamo de equipaje rediseñado'!$D226-'Reclamo de equipaje rediseñado'!$C226 -> 0.011111111 | F226: 0.2625 | G226: =F226-D226 -> 0.036805556 | H226: 41725 | I226: LAX | J226: B737-800 | K226: =VLOOKUP(J226,'Validacion reclamo de equipaje'!L:M,2,0) -> 189 | L226: =VLOOKUP(I226,'Validacion reclamo de equipaje'!H:I,2,0) -> Internacional | M226: Marzo
... A517: 3275 | B517: =VLOOKUP(Tabla6[[#This Row],['# Vuelo]],'Validacion reclamo de equipaje'!P:Q,2,0) -> AEROLINEAS DE AMERICA | C517: 0.44513889 | D517: 0.45347222 | E517: ='Reclamo de equipaje rediseñado'!$D517-'Reclamo de equipaje rediseñado'!$C517 -> 0.0083333333 | F517: 0.46875 | G517: =F517-D517 -> 0.015277778 | H517: 41729 | I517: DFW | J517: ER4 | K517: =VLOOKUP(J517,'Validacion reclamo de equipaje'!L:M,2,0) -> 50 | L517: =VLOOKUP(I517,'Validacion reclamo de equipaje'!H:I,2,0) -> Internacional | M517: Marzo
A518: 2840 | B518: =VLOOKUP(Tabla6[[#This Row],['# Vuelo]],'Validacion reclamo de equipaje'!P:Q,2,0) -> AEROLINEAS DE AMERICA | C518: 0.68611111 | D518: 0.69305556 | E518: ='Reclamo de equipaje rediseñado'!$D518-'Reclamo de equipaje rediseñado'!$C518 -> 0.0069444444 | F518: 0.70416667 | G518: =F518-D518 -> 0.011111111 | H518: 41715 | I518: SNA | J518: 320 | K518: =VLOOKUP(J518,'Validacion reclamo de equipaje'!L:M,2,0) -> 179 | L518: =VLOOKUP(I518,'Validacion reclamo de equipaje'!H:I,2,0) -> Internacional | M518: Marzo
A519: 2313 | B519: =VLOOKUP(Tabla6[[#This Row],['# Vuelo]],'Validacion reclamo de equipaje'!P:Q,2,0) -> AEROLINEAS DE AMERICA | C519: 0.92430556 | D519: 0.93611111 | E519: ='Reclamo de equipaje rediseñado'!$D519-'Reclamo de equipaje rediseñado'!$C519 -> 0.011805556 | F519: 0.95486111 | G519: =F519-D519 -> 0.01875 | H519: 41713 | I519: DFW | J519: M80 | K519: =VLOOKUP(J519,'Validacion reclamo de equipaje'!L:M,2,0) -> 182 | L519: =VLOOKUP(I519,'Validacion reclamo de equipaje'!H:I,2,0) -> Internacional | M519: Marzo
A520: 2313 | B520: =VLOOKUP(Tabla6[[#This Row],['# Vuelo]],'Validacion reclamo de equipaje'!P:Q,2,0) -> AEROLINEAS DE AMERICA | C520: 0.8375 | D520: 0.85347222 | E520: ='Reclamo de equipaje rediseñado'!$D520-'Reclamo de equipaje rediseñado'!$C520 -> 0.015972222 | F520: 0.86527778 | G520: =F520-D520 -> 0.011805556 | H520: 41719 | I520: DFW | J520: M80 | K520: =VLOOKUP(J520,'Validacion reclamo de equipaje'!L:M,2,0) -> 182 | L520: =VLOOKUP(I520,'Validacion reclamo de equipaje'!H:I,2,0) -> Internacional | M520: Marzo
A521: 2313 | B521: =VLOOKUP(Tabla6[[#This Row],['# Vuelo]],'Validacion reclamo de equipaje'!P:Q,2,0) -> AEROLINEAS DE AMERICA | C521: 0.82638889 | D521: 0.84375 | E521: ='Reclamo de equipaje rediseñado'!$D521-'Reclamo de equipaje rediseñado'!$C521 -> 0.017361111 | F521: 0.85555556 | G521: =F521-D521 -> 0.011805556 | H521: 41721 | I521: DFW | J521: M80 | K521: =VLOOKUP(J521,'Validacion reclamo de equipaje'!L:M,2,0) -> 182 | L521: =VLOOKUP(I521,'Validacion reclamo de equipaje'!H:I,2,0) -> Internacional | M521: Marzo
A522: 2313 | B522: =VLOOKUP(Tabla6[[#This Row],['# Vuelo]],'Validacion reclamo de equipaje'!P:Q,2,0) -> AEROLINEAS DE AMERICA | C522: 0.89791667 | D522: 0.91597222 | E522: ='Reclamo de equipaje rediseñado'!$D522-'Reclamo de equipaje rediseñado'!$C522 -> 0.018055556 | F522: 0.92361111 | G522: =F522-D522 -> 0.0076388889 | H522: 41724 | I522: DFW | J522: M80 | K522: =VLOOKUP(J522,'Validacion reclamo de equipaje'!L:M,2,0) -> 182 | L522: =VLOOKUP(I522,'Validacion reclamo de equipaje'!H:I,2,0) -> Internacional | M522: Marzo
A523: 2313 | B523: =VLOOKUP(Tabla6[[#This Row],['# Vuelo]],'Validacion reclamo de equipaje'!P:Q,2,0) -> AEROLINEAS DE AMERICA | C523: 0.84236111 | D523: 0.84861111 | E523: ='Reclamo de equipaje rediseñado'!$D523-'Reclamo de equipaje rediseñado'!$C523 -> 0.00625 | F523: 0.88194444 | G523: =F523-D523 -> 0.033333333 | H523: 41724 | I523: DFW | J523: M80 | K523: =VLOOKUP(J523,'Validacion reclamo de equipaje'!L:M,2,0) -> 182 | L523: =VLOOKUP(I523,'Validacion reclamo de equipaje'!H:I,2,0) -> Internacional | M523: Marzo
A524: 2313 | B524: =VLOOKUP(Tabla6[[#This Row],['# Vuelo]],'Validacion reclamo de equipaje'!P:Q,2,0) -> AEROLINEAS DE AMERICA | C524: 0.84583333 | D524: 0.86597222 | E524: ='Reclamo de equipaje rediseñado'!$D524-'Reclamo de equipaje rediseñado'!$C524 -> 0.020138889 | F524: 0.87569444 | G524: =F524-D524 -> 0.0097222222 | H524: 41728 | I524: DFW | J524: M80 | K524: =VLOOKUP(J524,'Validacion reclamo de equipaje'!L:M,2,0) -> 182 | L524: =VLOOKUP(I524,'Validacion reclamo de equipaje'!H:I,2,0) -> Internacional | M524: Marzo
A525: 387 | B525: =VLOOKUP(Tabla6[[#This Row],['# Vuelo]],'Validacion reclamo de equipaje'!P:Q,2,0) -> AEROLINEAS DE AMERICA | C525: 0.55555556 | D525: 0.57291667 | E525: ='Reclamo de equipaje rediseñado'!$D525-'Reclamo de equipaje rediseñado'!$C525 -> 0.017361111 | F525: 0.57986111 | G525: =F525-D525 -> 0.0069444444 | H525: 41714 | I525: DFW | J525: M80 | K525: =VLOOKUP(J525,'Validacion reclamo de equipaje'!L:M,2,0) -> 182 | L525: =VLOOKUP(I525,'Validacion reclamo de equipaje'!H:I,2,0) -> Internacional | M525: Marzo
A526: 387 | B526: =VLOOKUP(Tabla6[[#This Row],['# Vuelo]],'Validacion reclamo de equipaje'!P:Q,2,0) -> AEROLINEAS DE AMERICA | C526: 0.55555556 | D526: 0.57291667 | E526: ='Reclamo de equipaje rediseñado'!$D526-'Reclamo de equipaje rediseñado'!$C526 -> 0.017361111 | F526: 0.57986111 | G526: =F526-D526 -> 0.0069444444 | H526: 41720 | I526: DFW | J526: M80 | K526: =VLOOKUP(J526,'Validacion reclamo de equipaje'!L:M,2,0) -> 182 | L526: =VLOOKUP(I526,'Validacion reclamo de equipaje'!H:I,2,0) -> Internacional | M526: Marzo
A527: 387 | B527: =VLOOKUP(Tabla6[[#This Row],['# Vuelo]],'Validacion reclamo de equipaje'!P:Q,2,0) -> AEROLINEAS DE AMERICA | C527: 0.55 | D527: 0.56944444 | E527: ='Reclamo de equipaje rediseñado'!$D527-'Reclamo de equipaje rediseñado'!$C527 -> 0.019444444 | F527: 0.57986111 | G527: =F527-D527 -> 0.010416667 | H527: 41721 | I527: DFW | J527: M80 | K527: =VLOOKUP(J527,'Validacion reclamo de equipaje'!L:M,2,0) -> 182 | L527: =VLOOKUP(I527,'Validacion reclamo de equipaje'!H:I,2,0) -> Internacional | M527: Marzo
A528: 387 | B528: =VLOOKUP(Tabla6[[#This Row],['# Vuelo]],'Validacion reclamo de equipaje'!P:Q,2,0) -> AEROLINEAS DE AMERICA | C528: 0.55 | D528: 0.56736111 | E528: ='Reclamo de equipaje rediseñado'!$D528-'Reclamo de equipaje rediseñado'!$C528 -> 0.017361111 | F528: 0.58333333 | G528: =F528-D528 -> 0.015972222 | H528: 41722 | I528: DFW | J528: M80 | K528: =VLOOKUP(J528,'Validacion reclamo de equipaje'!L:M,2,0) -> 182 | L528: =VLOOKUP(I528,'Validacion reclamo de equipaje'!H:I,2,0) -> Internacional | M528: Marzo
A529: 387 | B529: =VLOOKUP(Tabla6[[#This Row],['# Vuelo]],'Validacion reclamo de equipaje'!P:Q,2,0) -> AEROLINEAS DE AMERICA | C529: 0.55902778 | D529: 0.56944444 | E529: ='Reclamo de equipaje rediseñado'!$D529-'Reclamo de equipaje rediseñado'!$C529 -> 0.010416667 | F529: 0.57916667 | G529: =F529-D529 -> 0.0097222222 | H529: 41723 | I529: DFW | J529: M80 | K529: =VLOOKUP(J529,'Validacion reclamo de equipaje'!L:M,2,0) -> 182 | L529: =VLOOKUP(I529,'Validacion reclamo de equipaje'!H:I,2,0) -> Internacional | M529: Marzo
A530: 387 | B530: =VLOOKUP(Tabla6[[#This Row],['# Vuelo]],'Validacion reclamo de equipaje'!P:Q,2,0) -> AEROLINEAS DE AMERICA | C530: 0.55347222 | D530: 0.56388889 | E530: ='Reclamo de equipaje rediseñado'!$D530-'Reclamo de equipaje rediseñado'!$C530 -> 0.010416667 | F530: 0.575 | G530: =F530-D530 -> 0.011111111 | H530: 41715 | I530: DFW | J530: M80 | K530: =VLOOKUP(J530,'Validacion reclamo de equipaje'!L:M,2,0) -> 182 | L530: =VLOOKUP(I530,'Validacion reclamo de equipaje'!H:I,2,0) -> Internacional | M530: Marzo
... A537: 387 | B537: =VLOOKUP(Tabla6[[#This Row],['# Vuelo]],'Validacion reclamo de equipaje'!P:Q,2,0) -> AEROLINEAS DE AMERICA | C537: 0.54236111 | D537: 0.55833333 | E537: ='Reclamo de equipaje rediseñado'!$D537-'Reclamo de equipaje rediseñado'!$C537 -> 0.015972222 | F537: 0.57291667 | G537: =F537-D537 -> 0.014583333 | H537: 41729 | I537: DFW | J537: M80 | K537: =VLOOKUP(J537,'Validacion reclamo de equipaje'!L:M,2,0) -> 182 | L537: =VLOOKUP(I537,'Validacion reclamo de equipaje'!H:I,2,0) -> Internacional | M537: Marzo
A538: 332 | B538: =VLOOKUP(Tabla6[[#This Row],['# Vuelo]],'Validacion reclamo de equipaje'!P:Q,2,0) -> AEROLINEAS DE AMERICA | C538: 0.54236111 | D538: 0.575 | E538: ='Reclamo de equipaje rediseñado'!$D538-'Reclamo de equipaje rediseñado'!$C538 -> 0.032638889 | F538: 0.57847222 | G538: =F538-D538 -> 0.0034722222 | H538: 41728 | I538: IAH | J538: 320 | K538: =VLOOKUP(J538,'Validacion reclamo de equipaje'!L:M,2,0) -> 179 | L538: =VLOOKUP(I538,'Validacion reclamo de equipaje'!H:I,2,0) -> Internacional | M538: Marzo
A539: 248 | B539: =VLOOKUP(Tabla6[[#This Row],['# Vuelo]],'Validacion reclamo de equipaje'!P:Q,2,0) -> VUELOS AL NORTE | C539: 0.46458333 | D539: 0.48055556 | E539: ='Reclamo de equipaje rediseñado'!$D539-'Reclamo de equipaje rediseñado'!$C539 -> 0.015972222 | F539: 0.49444444 | G539: =F539-D539 -> 0.013888889 | H539: 41718 | I539: LAX | J539: B737-800 | K539: =VLOOKUP(J539,'Validacion reclamo de equipaje'!L:M,2,0) -> 189 | L539: =VLOOKUP(I539,'Validacion reclamo de equipaje'!H:I,2,0) -> Internacional | M539: Marzo
A540: 242 | B540: =VLOOKUP(Tabla6[[#This Row],['# Vuelo]],'Validacion reclamo de equipaje'!P:Q,2,0) -> VUELOS AL NORTE | C540: 0.20902778 | D540: 0.21944444 | E540: ='Reclamo de equipaje rediseñado'!$D540-'Reclamo de equipaje rediseñado'!$C540 -> 0.010416667 | F540: 0.23611111 | G540: =F540-D540 -> 0.016666667 | H540: 41715 | I540: LAX | J540: B737-800 | K540: =VLOOKUP(J540,'Validacion reclamo de equipaje'!L:M,2,0) -> 189 | L540: =VLOOKUP(I540,'Validacion reclamo de equipaje'!H:I,2,0) -> Internacional | M540: Marzo
A541: 722 | B541: =VLOOKUP(Tabla6[[#This Row],['# Vuelo]],'Validacion reclamo de equipaje'!P:Q,2,0) -> COPA | C541: 0.95902778 | D541: 0.97986111 | E541: ='Reclamo de equipaje rediseñado'!$D541-'Reclamo de equipaje rediseñado'!$C541 -> 0.020833333 | F541: 0.9875 | G541: =F541-D541 -> 0.0076388889 | H541: 41721 | I541: PTY | J541: B737-800 | K541: =VLOOKUP(J541,'Validacion reclamo de equipaje'!L:M,2,0) -> 189 | L541: =VLOOKUP(I541,'Validacion reclamo de equipaje'!H:I,2,0) -> Internacional | M541: Marzo
A542: 722 | B542: =VLOOKUP(Tabla6[[#This Row],['# Vuelo]],'Validacion reclamo de equipaje'!P:Q,2,0) -> COPA | C542: 0.96111111 | D542: 0.97777778 | E542: ='Reclamo de equipaje rediseñado'!$D542-'Reclamo de equipaje rediseñado'!$C542 -> 0.016666667 | F542: 0.98541667 | G542: =F542-D542 -> 0.0076388889 | H542: 41713 | I542: PTY | J542: B737-800 | K542: =VLOOKUP(J542,'Validacion reclamo de equipaje'!L:M,2,0) -> 189 | L542: =VLOOKUP(I542,'Validacion reclamo de equipaje'!H:I,2,0) -> Internacional | M542: Marzo
A543: 722 | B543: =VLOOKUP(Tabla6[[#This Row],['# Vuelo]],'Validacion reclamo de equipaje'!P:Q,2,0) -> COPA | C543: 0.94791667 | D543: 0.96180556 | E543: ='Reclamo de equipaje rediseñado'!$D543-'Reclamo de equipaje rediseñado'!$C543 -> 0.013888889 | F543: 0.97013889 | G543: =F543-D543 -> 0.0083333333 | H543: 41715 | I543: PTY | J543: B737-800 | K543: =VLOOKUP(J543,'Validacion reclamo de equipaje'!L:M,2,0) -> 189 | L543: =VLOOKUP(I543,'Validacion reclamo de equipaje'!H:I,2,0) -> Internacional | M543: Marzo
A544: 722 | B544: =VLOOKUP(Tabla6[[#This Row],['# Vuelo]],'Validacion reclamo de equipaje'!P:Q,2,0) -> COPA | C544: 0.94097222 | D544: 0.95555556 | E544: ='Reclamo de equipaje rediseñado'!$D544-'Reclamo de equipaje rediseñado'!$C544 -> 0.014583333 | F544: 0.9625 | G544: =F544-D544 -> 0.0069444444 | H544: 41716 | I544: PTY | J544: B737-800 | K544: =VLOOKUP(J544,'Validacion reclamo de equipaje'!L:M,2,0) -> 189 | L544: =VLOOKUP(I544,'Validacion reclamo de equipaje'!H:I,2,0) -> Internacional | M544: Marzo
A545: 722 | B545: =VLOOKUP(Tabla6[[#This Row],['# Vuelo]],'Validacion reclamo de equipaje'!P:Q,2,0) -> COPA | C545: 0.94444444 | D545: 0.95833333 | E545: ='Reclamo de equipaje rediseñado'!$D545-'Reclamo de equipaje rediseñado'!$C545 -> 0.013888889 | F545: 0.99444444 | G545: =F545-D545 -> 0.036111111 | H545: 41717 | I545: PTY | J545: B737-800 | K545: =VLOOKUP(J545,'Validacion reclamo de equipaje'!L:M,2,0) -> 189 | L545: =VLOOKUP(I545,'Validacion reclamo de equipaje'!H:I,2,0) -> Internacional | M545: Marzo
A546: 722 | B546: =VLOOKUP(Tabla6[[#This Row],['# Vuelo]],'Validacion reclamo de equipaje'!P:Q,2,0) -> COPA | C546: 0.96111111 | D546: 0.97916667 | E546: ='Reclamo de equipaje rediseñado'!$D546-'Reclamo de equipaje rediseñado'!$C546 -> 0.018055556 | F546: 0.99027778 | G546: =F546-D546 -> 0.011111111 | H546: 41719 | I546: PTY | J546: B737-800 | K546: =VLOOKUP(J546,'Validacion reclamo de equipaje'!L:M,2,0) -> 189 | L546: =VLOOKUP(I546,'Validacion reclamo de equipaje'!H:I,2,0) -> Internacional | M546: Marzo
A547: 722 | B547: =VLOOKUP(Tabla6[[#This Row],['# Vuelo]],'Validacion reclamo de equipaje'!P:Q,2,0) -> COPA | C547: 0.95208333 | D547: 0.96736111 | E547: ='Reclamo de equipaje rediseñado'!$D547-'Reclamo de equipaje rediseñado'!$C547 -> 0.015277778 | F547: 0.97222222 | G547: =F547-D547 -> 0.0048611111 | H547: 41719 | I547: PTY | J547: B737-800 | K547: =VLOOKUP(J547,'Validacion reclamo de equipaje'!L:M,2,0) -> 189 | L547: =VLOOKUP(I547,'Validacion reclamo de equipaje'!H:I,2,0) -> Internacional | M547: Marzo
A548: 722 | B548: =VLOOKUP(Tabla6[[#This Row],['# Vuelo]],'Validacion reclamo de equipaje'!P:Q,2,0) -> COPA | C548: 0.94861111 | D548: 0.96527778 | E548: ='Reclamo de equipaje rediseñado'!$D548-'Reclamo de equipaje rediseñado'!$C548 -> 0.016666667 | F548: 0.97777778 | G548: =F548-D548 -> 0.0125 | H548: 41721 | I548: PTY | J548: B737-800 | K548: =VLOOKUP(J548,'Validacion reclamo de equipaje'!L:M,2,0) -> 189 | L548: =VLOOKUP(I548,'Validacion reclamo de equipaje'!H:I,2,0) -> Internacional | M548: Marzo
A549: 722 | B549: =VLOOKUP(Tabla6[[#This Row],['# Vuelo]],'Validacion reclamo de equipaje'!P:Q,2,0) -> COPA | C549: 0.94791667 | D549: 0.96319444 | E549: ='Reclamo de equipaje rediseñado'!$D549-'Reclamo de equipaje rediseñado'!$C549 -> 0.015277778 | F549: 0.97291667 | G549: =F549-D549 -> 0.0097222222 | H549: 41723 | I549: PTY | J549: B737-800 | K549: =VLOOKUP(J549,'Validacion reclamo de equipaje'!L:M,2,0) -> 189 | L549: =VLOOKUP(I549,'Validacion reclamo de equipaje'!H:I,2,0) -> Internacional | M549: Marzo
A550: 722 | B550: =VLOOKUP(Tabla6[[#This Row],['# Vuelo]],'Validacion reclamo de equipaje'!P:Q,2,0) -> COPA | C550: 0.95347222 | D550: 0.98055556 | E550: ='Reclamo de equipaje rediseñado'!$D550-'Reclamo de equipaje rediseñado'!$C550 -> 0.027083333 | F550: 1.0048611 | G550: =F550-D550 -> 0.024305556 | H550: 41724 | I550: PTY | J550: B737-800 | K550: =VLOOKUP(J550,'Validacion reclamo de equipaje'!L:M,2,0) -> 189 | L550: =VLOOKUP(I550,'Validacion reclamo de equipaje'!H:I,2,0) -> Internacional | M550: Marzo
... A556: 4560 | B556: =VLOOKUP(Tabla6[[#This Row],['# Vuelo]],'Validacion reclamo de equipaje'!P:Q,2,0) -> AVIONES ROJOS | C556: 0.57638889 | D556: 0.58958333 | E556: ='Reclamo de equipaje rediseñado'!$D556-'Reclamo de equipaje rediseñado'!$C556 -> 0.013194444 | F556: 0.59583333 | G556: =F556-D556 -> 0.00625 | H556: 41727 | I556: SLC | J556: CR9 | K556: =VLOOKUP(J556,'Validacion reclamo de equipaje'!L:M,2,0) -> 78 | L556: =VLOOKUP(I556,'Validacion reclamo de equipaje'!H:I,2,0) -> Internacional | M556: Marzo
A557: 573 | B557: =VLOOKUP(Tabla6[[#This Row],['# Vuelo]],'Validacion reclamo de equipaje'!P:Q,2,0) -> AVIONES ROJOS | C557: 0.24513889 | D557: 0.25069444 | E557: ='Reclamo de equipaje rediseñado'!$D557-'Reclamo de equipaje rediseñado'!$C557 -> 0.0055555556 | F557: 0.27638889 | G557: =F557-D557 -> 0.025694444 | H557: 41713 | I557: LAX | J557: 320 | K557: =VLOOKUP(J557,'Validacion reclamo de equipaje'!L:M,2,0) -> 179 | L557: =VLOOKUP(I557,'Validacion reclamo de equipaje'!H:I,2,0) -> Internacional | M557: Marzo
A558: 573 | B558: =VLOOKUP(Tabla6[[#This Row],['# Vuelo]],'Validacion reclamo de equipaje'!P:Q,2,0) -> AVIONES ROJOS | C558: 0.23472222 | D558: 0.24305556 | E558: ='Reclamo de equipaje rediseñado'!$D558-'Reclamo de equipaje rediseñado'!$C558 -> 0.0083333333 | F558: 0.26041667 | G558: =F558-D558 -> 0.017361111 | H558: 41715 | I558: LAX | J558: 320 | K558: =VLOOKUP(J558,'Validacion reclamo de equipaje'!L:M,2,0) -> 179 | L558: =VLOOKUP(I558,'Validacion reclamo de equipaje'!H:I,2,0) -> Internacional | M558: Marzo
A559: 573 | B559: =VLOOKUP(Tabla6[[#This Row],['# Vuelo]],'Validacion reclamo de equipaje'!P:Q,2,0) -> AVIONES ROJOS | C559: 0.24305556 | D559: 0.25347222 | E559: ='Reclamo de equipaje rediseñado'!$D559-'Reclamo de equipaje rediseñado'!$C559 -> 0.010416667 | F559: 0.28055556 | G559: =F559-D559 -> 0.027083333 | H559: 41716 | I559: LAX | J559: 320 | K559: =VLOOKUP(J559,'Validacion reclamo de equipaje'!L:M,2,0) -> 179 | L559: =VLOOKUP(I559,'Validacion reclamo de equipaje'!H:I,2,0) -> Internacional | M559: Marzo
A560: 573 | B560: =VLOOKUP(Tabla6[[#This Row],['# Vuelo]],'Validacion reclamo de equipaje'!P:Q,2,0) -> AVIONES ROJOS | C560: 0.23263889 | D560: 0.23819444 | E560: ='Reclamo de equipaje rediseñado'!$D560-'Reclamo de equipaje rediseñado'!$C560 -> 0.0055555556 | F560: 0.25 | G560: =F560-D560 -> 0.011805556 | H560: 41717 | I560: LAX | J560: 320 | K560: =VLOOKUP(J560,'Validacion reclamo de equipaje'!L:M,2,0) -> 179 | L560: =VLOOKUP(I560,'Validacion reclamo de equipaje'!H:I,2,0) -> Internacional | M560: Marzo
A561: 573 | B561: =VLOOKUP(Tabla6[[#This Row],['# Vuelo]],'Validacion reclamo de equipaje'!P:Q,2,0) -> AVIONES ROJOS | C561: 0.23263889 | D561: 0.23680556 | E561: ='Reclamo de equipaje rediseñado'!$D561-'Reclamo de equipaje rediseñado'!$C561 -> 0.0041666667 | F561: 0.24791667 | G561: =F561-D561 -> 0.011111111 | H561: 41719 | I561: LAX | J561: 320 | K561: =VLOOKUP(J561,'Validacion reclamo de equipaje'!L:M,2,0) -> 179 | L561: =VLOOKUP(I561,'Validacion reclamo de equipaje'!H:I,2,0) -> Internacional | M561: Marzo
A562: 573 | B562: =VLOOKUP(Tabla6[[#This Row],['# Vuelo]],'Validacion reclamo de equipaje'!P:Q,2,0) -> AVIONES ROJOS | C562: 0.24305556 | D562: 0.24513889 | E562: ='Reclamo de equipaje rediseñado'!$D562-'Reclamo de equipaje rediseñado'!$C562 -> 0.0020833333 | F562: 0.27152778 | G562: =F562-D562 -> 0.026388889 | H562: 41719 | I562: LAX | J562: 320 | K562: =VLOOKUP(J562,'Validacion reclamo de equipaje'!L:M,2,0) -> 179 | L562: =VLOOKUP(I562,'Validacion reclamo de equipaje'!H:I,2,0) -> Internacional | M562: Marzo
A563: 573 | B563: =VLOOKUP(Tabla6[[#This Row],['# Vuelo]],'Validacion reclamo de equipaje'!P:Q,2,0) -> AVIONES ROJOS | C563: 0.23194444 | D563: 0.23888889 | E563: ='Reclamo de equipaje rediseñado'!$D563-'Reclamo de equipaje rediseñado'!$C563 -> 0.0069444444 | F563: 0.26388889 | G563: =F563-D563 -> 0.025 | H563: 41721 | I563: LAX | J563: 320 | K563: =VLOOKUP(J563,'Validacion reclamo de equipaje'!L:M,2,0) -> 179 | L563: =VLOOKUP(I563,'Validacion reclamo de equipaje'!H:I,2,0) -> Internacional | M563: Marzo
A564: 573 | B564: =VLOOKUP(Tabla6[[#This Row],['# Vuelo]],'Validacion reclamo de equipaje'!P:Q,2,0) -> AVIONES ROJOS | C564: 0.22916667 | D564: 0.23888889 | E564: ='Reclamo de equipaje rediseñado'!$D564-'Reclamo de equipaje rediseñado'!$C564 -> 0.0097222222 | F564: 0.25833333 | G564: =F564-D564 -> 0.019444444 | H564: 41722 | I564: LAX | J564: 320 | K564: =VLOOKUP(J564,'Validacion reclamo de equipaje'!L:M,2,0) -> 179 | L564: =VLOOKUP(I564,'Validacion reclamo de equipaje'!H:I,2,0) -> Internacional | M564: Marzo
A565: 573 | B565: =VLOOKUP(Tabla6[[#This Row],['# Vuelo]],'Validacion reclamo de equipaje'!P:Q,2,0) -> AVIONES ROJOS | C565: 0.23888889 | D565: 0.24444444 | E565: ='Reclamo de equipaje rediseñado'!$D565-'Reclamo de equipaje rediseñado'!$C565 -> 0.0055555556 | F565: 0.25069444 | G565: =F565-D565 -> 0.00625 | H565: 41723 | I565: LAX | J565: 320 | K565: =VLOOKUP(J565,'Validacion reclamo de equipaje'!L:M,2,0) -> 179 | L565: =VLOOKUP(I565,'Validacion reclamo de equipaje'!H:I,2,0) -> Internacional | M565: Marzo
A566: 573 | B566: =VLOOKUP(Tabla6[[#This Row],['# Vuelo]],'Validacion reclamo de equipaje'!P:Q,2,0) -> AVIONES ROJOS | C566: 0.23333333 | D566: 0.24513889 | E566: ='Reclamo de equipaje rediseñado'!$D566-'Reclamo de equipaje rediseñado'!$C566 -> 0.011805556 | F566: 0.24930556 | G566: =F566-D566 -> 0.0041666667 | H566: 41724 | I566: LAX | J566: 320 | K566: =VLOOKUP(J566,'Validacion reclamo de equipaje'!L:M,2,0) -> 179 | L566: =VLOOKUP(I566,'Validacion reclamo de equipaje'!H:I,2,0) -> Internacional | M566: Marzo
A567: 573 | B567: =VLOOKUP(Tabla6[[#This Row],['# Vuelo]],'Validacion reclamo de equipaje'!P:Q,2,0) -> AVIONES ROJOS | C567: 0.23055556 | D567: 0.25486111 | E567: ='Reclamo de equipaje rediseñado'!$D567-'Reclamo de equipaje rediseñado'!$C567 -> 0.024305556 | F567: 0.28055556 | G567: =F567-D567 -> 0.025694444 | H567: 41725 | I567: LAX | J567: 320 | K567: =VLOOKUP(J567,'Validacion reclamo de equipaje'!L:M,2,0) -> 179 | L567: =VLOOKUP(I567,'Validacion reclamo de equipaje'!H:I,2,0) -> Internacional | M567: Marzo
A568: 573 | B568: =VLOOKUP(Tabla6[[#This Row],['# Vuelo]],'Validacion reclamo de equipaje'!P:Q,2,0) -> AVIONES ROJOS | C568: 0.23333333 | D568: 0.2375 | E568: ='Reclamo de equipaje rediseñado'!$D568-'Reclamo de equipaje rediseñado'!$C568 -> 0.0041666667 | F568: 0.25208333 | G568: =F568-D568 -> 0.014583333 | H568: 41727 | I568: LAX | J568: 320 | K568: =VLOOKUP(J568,'Validacion reclamo de equipaje'!L:M,2,0) -> 179 | L568: =VLOOKUP(I568,'Validacion reclamo de equipaje'!H:I,2,0) -> Internacional | M568: Marzo
... A735: 411 | B735: =VLOOKUP(Tabla6[[#This Row],['# Vuelo]],'Validacion reclamo de equipaje'!P:Q,2,0) -> INTERAVIÓN | C735: 0.83680556 | D735: 0.84375 | E735: ='Reclamo de equipaje rediseñado'!$D735-'Reclamo de equipaje rediseñado'!$C735 -> 0.0069444444 | F735: 0.85208333 | G735: =F735-D735 -> 0.0083333333 | H735: 41727 | I735: TIJ | J735: 320 | K735: =VLOOKUP(J735,'Validacion reclamo de equipaje'!L:M,2,0) -> 179 | L735: =VLOOKUP(I735,'Validacion reclamo de equipaje'!H:I,2,0) -> Nacional | M735: Marzo
A736: 248 | B736: =VLOOKUP(Tabla6[[#This Row],['# Vuelo]],'Validacion reclamo de equipaje'!P:Q,2,0) -> VUELOS AL NORTE | C736: 0.48402778 | D736: 0.49166667 | E736: ='Reclamo de equipaje rediseñado'!$D736-'Reclamo de equipaje rediseñado'!$C736 -> 0.0076388889 | F736: 0.51666667 | G736: =F736-D736 -> 0.025 | H736: 41715 | I736: LAS | J736: B737-800 | K736: =VLOOKUP(J736,'Validacion reclamo de equipaje'!L:M,2,0) -> 189 | L736: =VLOOKUP(I736,'Validacion reclamo de equipaje'!H:I,2,0) -> Internacional | M736: Marzo
A737: 236 | B737: =VLOOKUP(Tabla6[[#This Row],['# Vuelo]],'Validacion reclamo de equipaje'!P:Q,2,0) -> INTERAVIÓN | C737: 0.88888889 | D737: 0.90277778 | E737: ='Reclamo de equipaje rediseñado'!$D737-'Reclamo de equipaje rediseñado'!$C737 -> 0.013888889 | F737: 0.9125 | G737: =F737-D737 -> 0.0097222222 | H737: 41715 | I737: MTY | J737: 320 | K737: =VLOOKUP(J737,'Validacion reclamo de equipaje'!L:M,2,0) -> 179 | L737: =VLOOKUP(I737,'Validacion reclamo de equipaje'!H:I,2,0) -> Nacional | M737: Marzo
A738: 236 | B738: =VLOOKUP(Tabla6[[#This Row],['# Vuelo]],'Validacion reclamo de equipaje'!P:Q,2,0) -> INTERAVIÓN | C738: 0.87083333 | D738: 0.87986111 | E738: ='Reclamo de equipaje rediseñado'!$D738-'Reclamo de equipaje rediseñado'!$C738 -> 0.0090277778 | F738: 0.88888889 | G738: =F738-D738 -> 0.0090277778 | H738: 41716 | I738: MTY | J738: 320 | K738: =VLOOKUP(J738,'Validacion reclamo de equipaje'!L:M,2,0) -> 179 | L738: =VLOOKUP(I738,'Validacion reclamo de equipaje'!H:I,2,0) -> Nacional | M738: Marzo
A739: 236 | B739: =VLOOKUP(Tabla6[[#This Row],['# Vuelo]],'Validacion reclamo de equipaje'!P:Q,2,0) -> INTERAVIÓN | C739: 0.8875 | D739: 0.89583333 | E739: ='Reclamo de equipaje rediseñado'!$D739-'Reclamo de equipaje rediseñado'!$C739 -> 0.0083333333 | F739: 0.90138889 | G739: =F739-D739 -> 0.0055555556 | H739: 41721 | I739: MTY | J739: 320 | K739: =VLOOKUP(J739,'Validacion reclamo de equipaje'!L:M,2,0) -> 179 | L739: =VLOOKUP(I739,'Validacion reclamo de equipaje'!H:I,2,0) -> Nacional | M739: Marzo
A740: 236 | B740: =VLOOKUP(Tabla6[[#This Row],['# Vuelo]],'Validacion reclamo de equipaje'!P:Q,2,0) -> INTERAVIÓN | C740: 0.88611111 | D740: 0.89305556 | E740: ='Reclamo de equipaje rediseñado'!$D740-'Reclamo de equipaje rediseñado'!$C740 -> 0.0069444444 | F740: 0.9 | G740: =F740-D740 -> 0.0069444444 | H740: 41723 | I740: MTY | J740: 320 | K740: =VLOOKUP(J740,'Validacion reclamo de equipaje'!L:M,2,0) -> 179 | L740: =VLOOKUP(I740,'Validacion reclamo de equipaje'!H:I,2,0) -> Nacional | M740: Marzo
A741: 236 | B741: =VLOOKUP(Tabla6[[#This Row],['# Vuelo]],'Validacion reclamo de equipaje'!P:Q,2,0) -> INTERAVIÓN | C741: 0.89305556 | D741: 0.90277778 | E741: ='Reclamo de equipaje rediseñado'!$D741-'Reclamo de equipaje rediseñado'!$C741 -> 0.0097222222 | F741: 0.91597222 | G741: =F741-D741 -> 0.013194444 | H741: 41724 | I741: MTY | J741: 320 | K741: =VLOOKUP(J741,'Validacion reclamo de equipaje'!L:M,2,0) -> 179 | L741: =VLOOKUP(I741,'Validacion reclamo de equipaje'!H:I,2,0) -> Nacional | M741: Marzo
A742: 236 | B742: =VLOOKUP(Tabla6[[#This Row],['# Vuelo]],'Validacion reclamo de equipaje'!P:Q,2,0) -> INTERAVIÓN | C742: 0.89583333 | D742: 0.89861111 | E742: ='Reclamo de equipaje rediseñado'!$D742-'Reclamo de equipaje rediseñado'!$C742 -> 0.0027777778 | F742: 0.91527778 | G742: =F742-D742 -> 0.016666667 | H742: 41724 | I742: MTY | J742: 320 | K742: =VLOOKUP(J742,'Validacion reclamo de equipaje'!L:M,2,0) -> 179 | L742: =VLOOKUP(I742,'Validacion reclamo de equipaje'!H:I,2,0) -> Nacional | M742: Marzo
A743: 236 | B743: =VLOOKUP(Tabla6[[#This Row],['# Vuelo]],'Validacion reclamo de equipaje'!P:Q,2,0) -> INTERAVIÓN | C743: 0.89305556 | D743: 0.90486111 | E743: ='Reclamo de equipaje rediseñado'!$D743-'Reclamo de equipaje rediseñado'!$C743 -> 0.011805556 | F743: 0.90972222 | G743: =F743-D743 -> 0.0048611111 | H743: 41725 | I743: MTY | J743: 320 | K743: =VLOOKUP(J743,'Validacion reclamo de equipaje'!L:M,2,0) -> 179 | L743: =VLOOKUP(I743,'Validacion reclamo de equipaje'!H:I,2,0) -> Nacional | M743: Marzo
A744: 236 | B744: =VLOOKUP(Tabla6[[#This Row],['# Vuelo]],'Validacion reclamo de equipaje'!P:Q,2,0) -> INTERAVIÓN | C744: 0.88541667 | D744: 0.89375 | E744: ='Reclamo de equipaje rediseñado'!$D744-'Reclamo de equipaje rediseñado'!$C744 -> 0.0083333333 | F744: 0.90555556 | G744: =F744-D744 -> 0.011805556 | H744: 41726 | I744: MTY | J744: 320 | K744: =VLOOKUP(J744,'Validacion reclamo de equipaje'!L:M,2,0) -> 179 | L744: =VLOOKUP(I744,'Validacion reclamo de equipaje'!H:I,2,0) -> Nacional | M744: Marzo
A745: 236 | B745: =VLOOKUP(Tabla6[[#This Row],['# Vuelo]],'Validacion reclamo de equipaje'!P:Q,2,0) -> INTERAVIÓN | C745: 0.88541667 | D745: 0.89375 | E745: ='Reclamo de equipaje rediseñado'!$D745-'Reclamo de equipaje rediseñado'!$C745 -> 0.0083333333 | F745: 0.90555556 | G745: =F745-D745 -> 0.011805556 | H745: 41726 | I745: MTY | J745: 320 | K745: =VLOOKUP(J745,'Validacion reclamo de equipaje'!L:M,2,0) -> 179 | L745: =VLOOKUP(I745,'Validacion reclamo de equipaje'!H:I,2,0) -> Nacional | M745: Marzo
A746: 230 | B746: =VLOOKUP(Tabla6[[#This Row],['# Vuelo]],'Validacion reclamo de equipaje'!P:Q,2,0) -> INTERAVIÓN | C746: 0.32777778 | D746: 0.34027778 | E746: ='Reclamo de equipaje rediseñado'!$D746-'Reclamo de equipaje rediseñado'!$C746 -> 0.0125 | F746: 0.34236111 | G746: =F746-D746 -> 0.0020833333 | H746: 41716 | I746: CUU | J746: ER4 | K746: =VLOOKUP(J746,'Validacion reclamo de equipaje'!L:M,2,0) -> 50 | L746: =VLOOKUP(I746,'Validacion reclamo de equipaje'!H:I,2,0) -> Nacional | M746: Marzo
A747: 230 | B747: =VLOOKUP(Tabla6[[#This Row],['# Vuelo]],'Validacion reclamo de equipaje'!P:Q,2,0) -> INTERAVIÓN | C747: 0.31944444 | D747: 0.32986111 | E747: ='Reclamo de equipaje rediseñado'!$D747-'Reclamo de equipaje rediseñado'!$C747 -> 0.010416667 | F747: 0.3375 | G747: =F747-D747 -> 0.0076388889 | H747: 41717 | I747: CUU | J747: ER4 | K747: =VLOOKUP(J747,'Validacion reclamo de equipaje'!L:M,2,0) -> 50 | L747: =VLOOKUP(I747,'Validacion reclamo de equipaje'!H:I,2,0) -> Nacional | M747: Marzo
A748: 230 | B748: =VLOOKUP(Tabla6[[#This Row],['# Vuelo]],'Validacion reclamo de equipaje'!P:Q,2,0) -> INTERAVIÓN | C748: 0.34305556 | D748: 0.34791667 | E748: ='Reclamo de equipaje rediseñado'!$D748-'Reclamo de equipaje rediseñado'!$C748 -> 0.0048611111 | F748: 0.35625 | G748: =F748-D748 -> 0.0083333333 | H748: 41718 | I748: CUU | J748: ER4 | K748: =VLOOKUP(J748,'Validacion reclamo de equipaje'!L:M,2,0) -> 50 | L748: =VLOOKUP(I748,'Validacion reclamo de equipaje'!H:I,2,0) -> Nacional | M748: Marzo
A749: 230 | B749: =VLOOKUP(Tabla6[[#This Row],['# Vuelo]],'Validacion reclamo de equipaje'!P:Q,2,0) -> INTERAVIÓN | C749: 0.43402778 | D749: 0.44097222 | E749: ='Reclamo de equipaje rediseñado'!$D749-'Reclamo de equipaje rediseñado'!$C749 -> 0.0069444444 | F749: 0.44444444 | G749: =F749-D749 -> 0.0034722222 | H749: 41720 | I749: CUU | J749: ER4 | K749: =VLOOKUP(J749,'Validacion reclamo de equipaje'!L:M,2,0) -> 50 | L749: =VLOOKUP(I749,'Validacion reclamo de equipaje'!H:I,2,0) -> Nacional | M749: Marzo
A750: 230 | B750: =VLOOKUP(Tabla6[[#This Row],['# Vuelo]],'Validacion reclamo de equipaje'!P:Q,2,0) -> INTERAVIÓN | C750: 0.33402778 | D750: 0.34166667 | E750: ='Reclamo de equipaje rediseñado'!$D750-'Reclamo de equipaje rediseñado'!$C750 -> 0.0076388889 | F750: 0.34375 | G750: =F750-D750 -> 0.0020833333 | H750: 41725 | I750: CUU | J750: ER4 | K750: =VLOOKUP(J750,'Validacion reclamo de equipaje'!L:M,2,0) -> 50 | L750: =VLOOKUP(I750,'Validacion reclamo de equipaje'!H:I,2,0) -> Nacional | M750: Marzo
A751: 230 | B751: =VLOOKUP(Tabla6[[#This Row],['# Vuelo]],'Validacion reclamo de equipaje'!P:Q,2,0) -> INTERAVIÓN | C751: 0.41527778 | D751: 0.42291667 | E751: ='Reclamo de equipaje rediseñado'!$D751-'Reclamo de equipaje rediseñado'!$C751 -> 0.0076388889 | F751: 0.425 | G751: =F751-D751 -> 0.0020833333 | H751: 41727 | I751: CUU | J751: ER4 | K751: =VLOOKUP(J751,'Validacion reclamo de equipaje'!L:M,2,0) -> 50 | L751: =VLOOKUP(I751,'Validacion reclamo de equipaje'!H:I,2,0) -> Nacional | M751: Marzo
A752: 221 | B752: =VLOOKUP(Tabla6[[#This Row],['# Vuelo]],'Validacion reclamo de equipaje'!P:Q,2,0) -> INTERAVIÓN | C752: 0.44027778 | D752: 0.45277778 | E752: ='Reclamo de equipaje rediseñado'!$D752-'Reclamo de equipaje rediseñado'!$C752 -> 0.0125 | F752: 0.46111111 | G752: =F752-D752 -> 0.0083333333 | H752: 41718 | I752: CUU | J752: ER4 | K752: =VLOOKUP(J752,'Validacion reclamo de equipaje'!L:M,2,0) -> 50 | L752: =VLOOKUP(I752,'Validacion reclamo de equipaje'!H:I,2,0) -> Nacional | M752: Marzo
A753: 585 | B753: =VLOOKUP(Tabla6[[#This Row],['# Vuelo]],'Validacion reclamo de equipaje'!P:Q,2,0) -> MEXICO AEREO | C753: 0.76666667 | D753: 0.77638889 | E753: ='Reclamo de equipaje rediseñado'!$D753-'Reclamo de equipaje rediseñado'!$C753 -> 0.0097222222 | F753: 0.78472222 | G753: =F753-D753 -> 0.0083333333 | H753: 41715 | I753: CUN | J753: B737-800 | K753: =VLOOKUP(J753,'Validacion reclamo de equipaje'!L:M,2,0) -> 189 | L753: =VLOOKUP(I753,'Validacion reclamo de equipaje'!H:I,2,0) -> Nacional | M753: Marzo
A754: 585 | B754: =VLOOKUP(Tabla6[[#This Row],['# Vuelo]],'Validacion reclamo de equipaje'!P:Q,2,0) -> MEXICO AEREO | C754: 0.71180556 | D754: 0.72152778 | E754: ='Reclamo de equipaje rediseñado'!$D754-'Reclamo de equipaje rediseñado'!$C754 -> 0.0097222222 | F754: 0.72569444 | G754: =F754-D754 -> 0.0041666667 | H754: 41716 | I754: CUN | J754: B737-800 | K754: =VLOOKUP(J754,'Validacion reclamo de equipaje'!L:M,2,0) -> 189 | L754: =VLOOKUP(I754,'Validacion reclamo de equipaje'!H:I,2,0) -> Nacional | M754: Marzo
A755: 585 | B755: =VLOOKUP(Tabla6[[#This Row],['# Vuelo]],'Validacion reclamo de equipaje'!P:Q,2,0) -> MEXICO AEREO | C755: 0.71666667 | D755: 0.72430556 | E755: ='Reclamo de equipaje rediseñado'!$D755-'Reclamo de equipaje rediseñado'!$C755 -> 0.0076388889 | F755: 0.72916667 | G755: =F755-D755 -> 0.0048611111 | H755: 41717 | I755: CUN | J755: B737-800 | K755: =VLOOKUP(J755,'Validacion reclamo de equipaje'!L:M,2,0) -> 189 | L755: =VLOOKUP(I755,'Validacion reclamo de equipaje'!H:I,2,0) -> Nacional | M755: Marzo
A756: 585 | B756: =VLOOKUP(Tabla6[[#This Row],['# Vuelo]],'Validacion reclamo de equipaje'!P:Q,2,0) -> MEXICO AEREO | C756: 0.87847222 | D756: 0.88819444 | E756: ='Reclamo de equipaje rediseñado'!$D756-'Reclamo de equipaje rediseñado'!$C756 -> 0.0097222222 | F756: 0.89791667 | G756: =F756-D756 -> 0.0097222222 | H756: 41719 | I756: CUN | J756: B737-800 | K756: =VLOOKUP(J756,'Validacion reclamo de equipaje'!L:M,2,0) -> 189 | L756: =VLOOKUP(I756,'Validacion reclamo de equipaje'!H:I,2,0) -> Nacional | M756: Marzo
A757: 585 | B757: =VLOOKUP(Tabla6[[#This Row],['# Vuelo]],'Validacion reclamo de equipaje'!P:Q,2,0) -> MEXICO AEREO | C757: 0.63402778 | D757: 0.64236111 | E757: ='Reclamo de equipaje rediseñado'!$D757-'Reclamo de equipaje rediseñado'!$C757 -> 0.0083333333 | F757: 0.64583333 | G757: =F757-D757 -> 0.0034722222 | H757: 41720 | I757: CUN | J757: B737-800 | K757: =VLOOKUP(J757,'Validacion reclamo de equipaje'!L:M,2,0) -> 189 | L757: =VLOOKUP(I757,'Validacion reclamo de equipaje'!H:I,2,0) -> Nacional | M757: Marzo
... A836: 1590 | B836: =VLOOKUP(Tabla6[[#This Row],['# Vuelo]],'Validacion reclamo de equipaje'!P:Q,2,0) -> UNIDOS VOLAMOS | C836: 0.17361111 | D836: 0.19166667 | E836: ='Reclamo de equipaje rediseñado'!$D836-'Reclamo de equipaje rediseñado'!$C836 -> 0.018055556 | F836: 0.21458333 | G836: =F836-D836 -> 0.022916667 | H836: 41727 | I836: SFO | J836: B737-700 | K836: =VLOOKUP(J836,'Validacion reclamo de equipaje'!L:M,2,0) -> 126 | L836: =VLOOKUP(I836,'Validacion reclamo de equipaje'!H:I,2,0) -> Internacional | M836: Marzo
A837: 480 | B837: =VLOOKUP(Tabla6[[#This Row],['# Vuelo]],'Validacion reclamo de equipaje'!P:Q,2,0) -> UNIDOS VOLAMOS | C837: 0.20277778 | D837: 0.21875 | E837: ='Reclamo de equipaje rediseñado'!$D837-'Reclamo de equipaje rediseñado'!$C837 -> 0.015972222 | F837: 0.22708333 | G837: =F837-D837 -> 0.0083333333 | H837: 41715 | I837: SFO | J837: 320 | K837: =VLOOKUP(J837,'Validacion reclamo de equipaje'!L:M,2,0) -> 179 | L837: =VLOOKUP(I837,'Validacion reclamo de equipaje'!H:I,2,0) -> Internacional | M837: Marzo
A838: 480 | B838: =VLOOKUP(Tabla6[[#This Row],['# Vuelo]],'Validacion reclamo de equipaje'!P:Q,2,0) -> UNIDOS VOLAMOS | C838: 0.20208333 | D838: 0.21527778 | E838: ='Reclamo de equipaje rediseñado'!$D838-'Reclamo de equipaje rediseñado'!$C838 -> 0.013194444 | F838: 0.225 | G838: =F838-D838 -> 0.0097222222 | H838: 41716 | I838: SFO | J838: 320 | K838: =VLOOKUP(J838,'Validacion reclamo de equipaje'!L:M,2,0) -> 179 | L838: =VLOOKUP(I838,'Validacion reclamo de equipaje'!H:I,2,0) -> Internacional | M838: Marzo
A839: 480 | B839: =VLOOKUP(Tabla6[[#This Row],['# Vuelo]],'Validacion reclamo de equipaje'!P:Q,2,0) -> UNIDOS VOLAMOS | C839: 0.18680556 | D839: 0.20208333 | E839: ='Reclamo de equipaje rediseñado'!$D839-'Reclamo de equipaje rediseñado'!$C839 -> 0.015277778 | F839: 0.22916667 | G839: =F839-D839 -> 0.027083333 | H839: 41717 | I839: SFO | J839: 320 | K839: =VLOOKUP(J839,'Validacion reclamo de equipaje'!L:M,2,0) -> 179 | L839: =VLOOKUP(I839,'Validacion reclamo de equipaje'!H:I,2,0) -> Internacional | M839: Marzo
A840: 480 | B840: =VLOOKUP(Tabla6[[#This Row],['# Vuelo]],'Validacion reclamo de equipaje'!P:Q,2,0) -> UNIDOS VOLAMOS | C840: 0.23194444 | D840: 0.2375 | E840: ='Reclamo de equipaje rediseñado'!$D840-'Reclamo de equipaje rediseñado'!$C840 -> 0.0055555556 | F840: 0.24791667 | G840: =F840-D840 -> 0.010416667 | H840: 41719 | I840: SFO | J840: 320 | K840: =VLOOKUP(J840,'Validacion reclamo de equipaje'!L:M,2,0) -> 179 | L840: =VLOOKUP(I840,'Validacion reclamo de equipaje'!H:I,2,0) -> Internacional | M840: Marzo
A841: 480 | B841: =VLOOKUP(Tabla6[[#This Row],['# Vuelo]],'Validacion reclamo de equipaje'!P:Q,2,0) -> UNIDOS VOLAMOS | C841: 0.19861111 | D841: 0.21319444 | E841: ='Reclamo de equipaje rediseñado'!$D841-'Reclamo de equipaje rediseñado'!$C841 -> 0.014583333 | F841: 0.25694444 | G841: =F841-D841 -> 0.04375 | H841: 41719 | I841: SFO | J841: 320 | K841: =VLOOKUP(J841,'Validacion reclamo de equipaje'!L:M,2,0) -> 179 | L841: =VLOOKUP(I841,'Validacion reclamo de equipaje'!H:I,2,0) -> Internacional | M841: Marzo
A842: 480 | B842: =VLOOKUP(Tabla6[[#This Row],['# Vuelo]],'Validacion reclamo de equipaje'!P:Q,2,0) -> UNIDOS VOLAMOS | C842: 0.2 | D842: 0.21597222 | E842: ='Reclamo de equipaje rediseñado'!$D842-'Reclamo de equipaje rediseñado'!$C842 -> 0.015972222 | F842: 0.22638889 | G842: =F842-D842 -> 0.010416667 | H842: 41723 | I842: SFO | J842: 320 | K842: =VLOOKUP(J842,'Validacion reclamo de equipaje'!L:M,2,0) -> 179 | L842: =VLOOKUP(I842,'Validacion reclamo de equipaje'!H:I,2,0) -> Internacional | M842: Marzo
A843: 480 | B843: =VLOOKUP(Tabla6[[#This Row],['# Vuelo]],'Validacion reclamo de equipaje'!P:Q,2,0) -> UNIDOS VOLAMOS | C843: 0.18611111 | D843: 0.19791667 | E843: ='Reclamo de equipaje rediseñado'!$D843-'Reclamo de equipaje rediseñado'!$C843 -> 0.011805556 | F843: 0.22013889 | G843: =F843-D843 -> 0.022222222 | H843: 41724 | I843: SFO | J843: 320 | K843: =VLOOKUP(J843,'Validacion reclamo de equipaje'!L:M,2,0) -> 179 | L843: =VLOOKUP(I843,'Validacion reclamo de equipaje'!H:I,2,0) -> Internacional | M843: Marzo
A844: 480 | B844: =VLOOKUP(Tabla6[[#This Row],['# Vuelo]],'Validacion reclamo de equipaje'!P:Q,2,0) -> UNIDOS VOLAMOS | C844: 0.20138889 | D844: 0.21944444 | E844: ='Reclamo de equipaje rediseñado'!$D844-'Reclamo de equipaje rediseñado'!$C844 -> 0.018055556 | F844: 0.23402778 | G844: =F844-D844 -> 0.014583333 | H844: 41724 | I844: SFO | J844: 320 | K844: =VLOOKUP(J844,'Validacion reclamo de equipaje'!L:M,2,0) -> 179 | L844: =VLOOKUP(I844,'Validacion reclamo de equipaje'!H:I,2,0) -> Internacional | M844: Marzo
...

Sheet Validacion reclamo de equipaje
A1: LÍNEA AÉREA | C1: # Vuelo | D1: Nacional/ Internacional | H1: Procedencia | I1: Nacional/ Internacional | L1: Equipo | M1: Capacidad | P1: # Vuelo | Q1: LÍNEA AÉREA
A2: MEXICO AEREO | C2: 8851 | D2: Nacional | H2: MEX | I2: Nacional | L2: ER4 | M2: 50 | P2: 8851 | Q2: MEXICO AEREO
A3: VUELOS AL NORTE | C3: 8702 | D3: Internacional | H3: QRO | I3: Nacional | P3: 8702 | Q3: MEXICO AEREO
A4: AEROLINEAS DE AMERICA | C4: 3120 | H4: TLC | I4: Nacional | L4: B737-800 | M4: 189 | P4: 3120 | Q4: MEXICO AEREO
A5: COPA | C5: 2811 | H5: HMO | I5: Nacional | L5: B737-700 | M5: 126 | P5: 2811 | Q5: MEXICO AEREO
A6: AVIONES ROJOS | C6: 2625 | H6: MID | I6: Nacional | L6: E90 | M6: 99 | P6: 2625 | Q6: MEXICO AEREO
A7: INTERAVIÓN | C7: 2622 | H7: PVR | I7: Nacional | L7: 320 | M7: 179 | P7: 2622 | Q7: MEXICO AEREO
A8: GRANRENTA | C8: 2621 | H8: SAT | I8: Nacional | L8: M80 | M8: 182 | P8: 2621 | Q8: MEXICO AEREO
A9: TOR | C9: 2501 | H9: CUU | I9: Nacional | L9: CR9 | M9: 78 | P9: 2501 | Q9: MEXICO AEREO
A10: UNIDOS VOLAMOS | C10: 2469 | H10: TIJ | I10: Nacional | L10: CRJ 700 | M10: 78 | P10: 2469 | Q10: MEXICO AEREO
A11: VIAS AÉREAS DE USA | C11: 2335 | H11: MTY | I11: Nacional | L11: A319 | M11: 142 | P11: 2335 | Q11: MEXICO AEREO
A12: BARATA Y MORADA | C12: 2320 | H12: CUL | I12: Nacional | L12: 738 | M12: 189 | P12: 2320 | Q12: MEXICO AEREO
A13: VUELOS AL NORTE AIRLINES | C13: 2301 | H13: CJS | I13: Nacional | L13: ER4 | M13: 50 | P13: 2301 | Q13: MEXICO AEREO
A14: COPA AIRLINES | C14: 2277 | H14: ZCL | I14: Nacional | L14: 733 | M14: 169 | P14: 2277 | Q14: MEXICO AEREO
A15: AVIONES ROJOS AIRLINES | C15: 2219 | H15: LAX | I15: Internacional | L15: B737-800 | M15: 169 | P15: 2219 | Q15: MEXICO AEREO
A16: GRANRENTA | C16: 2193 | H16: ONT | I16: Internacional | L16: CRJ700 | M16: 78 | P16: 2193 | Q16: MEXICO AEREO
A17: AEROLÍNEA TOR | C17: 2185 | H17: SFO | I17: Internacional | L17: 737 | M17: 169 | P17: 2185 | Q17: MEXICO AEREO
A18: UNIDOS VOLAMOS AIRLINES | C18: 2184 | H18: ORD | I18: Internacional | L18: B757-200 | M18: 239 | P18: 2184 | Q18: MEXICO AEREO
A19: INTERAVIÓN | C19: 2122 | H19: CUN | I19: Nacional | L19: SU1 | M19: 179 | P19: 2122 | Q19: MEXICO AEREO
C20: 2121 | H20: SFO | I20: Nacional | P20: 2121 | Q20: MEXICO AEREO
C21: 2058 | H21: SEA | I21: Internacional | P21: 2058 | Q21: MEXICO AEREO
C22: 2028 | H22: IAH | I22: Internacional | P22: 2028 | Q22: MEXICO AEREO
C23: 2027 | H23: DFW | I23: Internacional | P23: 2027 | Q23: MEXICO AEREO
C24: 2015 | H24: SNA | I24: Internacional | P24: 2015 | Q24: MEXICO AEREO
C25: 2012 | H25: PTY | I25: Internacional | P25: 2012 | Q25: MEXICO AEREO
C26: 2011 | H26: SLC | I26: Internacional | P26: 2011 | Q26: MEXICO AEREO
C27: 2010 | H27: ATL | I27: Internacional | P27: 2010 | Q27: MEXICO AEREO
C28: 1114 | H28: SAT | I28: Internacional | P28: 1114 | Q28: MEXICO AEREO
C29: L | H29: SJD | I29: Nacional | P29: L | Q29: MEXICO AEREO
C30: 785 | H30: MXL | I30: Nacional | P30: 785 | Q30: MEXICO AEREO
C31: 783 | H31: LAS | I31: Internacional | P31: 783 | Q31: MEXICO AEREO
C32: 781 | H32: PHX | I32: Internacional | P32: 781 | Q32: MEXICO AEREO
C33: 779 | H33: OAK | I33: Internacional | P33: 779 | Q33: MEXICO AEREO
C34: 775 | H34: IAH | I34: Nacional | P34: 775 | Q34: MEXICO AEREO
C35: 773 | H35: SMF | I35: Internacional | P35: 773 | Q35: MEXICO AEREO
C36: 771 | H36: FAT | I36: Internacional | P36: 771 | Q36: MEXICO AEREO
C37: 663 | H37: MDW | I37: Internacional | P37: 663 | Q37: MEXICO AEREO
C38: 661 | H38: SJC | I38: Internacional | P38: 661 | Q38: MEXICO AEREO
C39: 585 | H39: LAX | I39: Nacional | P39: 585 | Q39: MEXICO AEREO
C40: 466 | H40: VER | I40: Nacional | P40: 466 | Q40: MEXICO AEREO
C41: 286 | H41: TGZ | I41: Nacional | P41: 286 | Q41: MEXICO AEREO
... C44: 252 | H44: LMM | I44: Nacional | P44: 252 | Q44: MEXICO AEREO
C45: 228 | H45: 631 | I45: Nacional | P45: 228 | Q45: MEXICO AEREO
C46: 225 | H46: MXL | I46: Internacional | P46: 225 | Q46: MEXICO AEREO
C47: 224 | H47: MTV | I47: Nacional | P47: 224 | Q47: MEXICO AEREO
C48: 215 | H48: VER | I48: Internacional | P48: 215 | Q48: MEXICO AEREO
C49: 214 | H49: MEX | I49: Internacional | P49: 214 | Q49: MEXICO AEREO
C50: 186 | H50: SID | I50: Nacional | P50: 186 | Q50: MEXICO AEREO
C51: 156 | H51: AGU | I51: Nacional | P51: 156 | Q51: MEXICO AEREO
C52: 128 | H52: DGO | I52: Nacional | P52: 128 | Q52: MEXICO AEREO
C53: 126 | H53: AIH | I53: Internacional | P53: 126 | Q53: MEXICO AEREO
C54: 120 | H54: 620 | I54: Nacional | P54: 120 | Q54: MEXICO AEREO
C55: 108 | H55: SAN | I55: Internacional | P55: 108 | Q55: MEXICO AEREO
C56: 104 | H56: TLC | I56: Internacional | P56: 104 | Q56: MEXICO AEREO
C57: 102 | H57: MTY | I57: Internacional | P57: 102 | Q57: MEXICO AEREO
C58: 100 | P58: 100 | Q58: MEXICO AEREO
C59: 248 | P59: 783 | Q59: VUELOS AL NORTE
C60: 242 | P60: 248 | Q60: VUELOS AL NORTE
C61: 226 | P61: 242 | Q61: VUELOS AL NORTE
C62: 4525 | P62: 226 | Q62: VUELOS AL NORTE
C63: 3275 | P63: 4525 | Q63: AEROLINEAS DE AMERICA
C64: 2840 | P64: 3275 | Q64: AEROLINEAS DE AMERICA
C65: 2313 | P65: 2840 | Q65: AEROLINEAS DE AMERICA
C66: 387 | P66: 2313 | Q66: AEROLINEAS DE AMERICA
C67: 332 | P67: 387 | Q67: AEROLINEAS DE AMERICA
C68: 722 | P68: 332 | Q68: AEROLINEAS DE AMERICA
C69: 4560 | P69: 248 | Q69: AEROLINEAS DE AMERICA
... C223: 2236 | P223: 2121 | Q223: AEROLÍNEA TOR
P224: 8026 | Q224: AEROLÍNEA TOR
P225: 221 | Q225: UNIDOS VOLAMOS AIRLINES
P226: 322 | Q226: UNIDOS VOLAMOS AIRLINES
P227: 480 | Q227: UNIDOS VOLAMOS AIRLINES
P228: 1590 | Q228: UNIDOS VOLAMOS AIRLINES
P229: 4211 | Q229: UNIDOS VOLAMOS AIRLINES
P230: 4354 | Q230: UNIDOS VOLAMOS AIRLINES
P231: 4394 | Q231: UNIDOS VOLAMOS AIRLINES
P232: 4489 | Q232: UNIDOS VOLAMOS AIRLINES
P233: 4525 | Q233: UNIDOS VOLAMOS AIRLINES
P234: 2927 | Q234: VIAS AÉREAS DE USA
P235: 150 | Q235: BARATA Y MORADA
... P276: 230 | Q276: INTERAVIÓN
